{"kv14.2":{"kv14.2:0.1":{"pli":"Kathāvatthu ","html":"<article id='kv14.2'><header><ul><li class='division'>{}</li>"},"kv14.2:0.2":{"pli":"Mahāpaṇṇāsaka ","html":"<li>{}</li>"},"kv14.2:0.3":{"pli":"Cuddasamavagga ","html":"<li>{}</li></ul>"},"kv14.2:0.4":{"pli":"Saḷāyatanuppattikathā ","html":"<h1 class='sutta-title'>{}</h1></header>"},"kv14.2:1.1":{"pli":"Saḷāyatanaṃ apubbaṃ acarimaṃ mātukucchismiṃ saṇṭhātīti? ","html":"<p data-doxy='orthodox'>{}"},"kv14.2:1.2":{"pli":"Āmantā. ","html":"{}"},"kv14.2:1.3":{"pli":"Sabbaṅgapaccaṅgī ahīnindriyo mātukucchismiṃ okkamatīti? ","html":"{}"},"kv14.2:1.4":{"pli":"Na hevaṃ vattabbe …pe…. ","html":"{}</p>"},"kv14.2:2.1":{"pli":"Upapattesiyena cittena cakkhāyatanaṃ saṇṭhātīti? ","html":"<p data-doxy='orthodox'>{}"},"kv14.2:2.2":{"pli":"Āmantā. ","html":"{}"},"kv14.2:2.3":{"pli":"Upapattesiyena cittena hatthā saṇṭhanti, pādā saṇṭhanti, sīsaṃ saṇṭhāti, kaṇṇo saṇṭhāti, nāsikā saṇṭhāti, mukhaṃ saṇṭhāti, dantā saṇṭhantīti? ","html":"{}"},"kv14.2:2.4":{"pli":"Na hevaṃ vattabbe …pe…. ","html":"{}</p>"},"kv14.2:3.1":{"pli":"Upapattesiyena cittena sotāyatanaṃ …pe… ","html":"<p data-doxy='orthodox'>{}"},"kv14.2:3.2":{"pli":"ghānāyatanaṃ …pe… ","html":"{}"},"kv14.2:3.3":{"pli":"jivhāyatanaṃ saṇṭhātīti? ","html":"{}"},"kv14.2:3.4":{"pli":"Āmantā. ","html":"{}"},"kv14.2:3.5":{"pli":"Upapattesiyena cittena hatthā saṇṭhanti, pādā saṇṭhanti, sīsaṃ saṇṭhāti, kaṇṇo saṇṭhāti, nāsikā saṇṭhāti, mukhaṃ saṇṭhāti, dantā saṇṭhantīti? ","html":"{}"},"kv14.2:3.6":{"pli":"Na hevaṃ vattabbe …pe…. ","html":"{}</p>"},"kv14.2:4.1":{"pli":"Mātukucchigatassa pacchā cakkhāyatanaṃ uppajjatīti? ","html":"<p data-doxy='heterodox'>{}"},"kv14.2:4.2":{"pli":"Āmantā. ","html":"{}"},"kv14.2:4.3":{"pli":"Mātukucchismiṃ cakkhupaṭilābhāya kammaṃ karotīti? ","html":"{}"},"kv14.2:4.4":{"pli":"Na hevaṃ vattabbe …pe… ","html":"{}"},"kv14.2:4.5":{"pli":"mātukucchigatassa pacchā sotāyatanaṃ …pe… ","html":"{}"},"kv14.2:4.6":{"pli":"ghānāyatanaṃ …pe… ","html":"{}"},"kv14.2:4.7":{"pli":"jivhāyatanaṃ uppajjatīti? ","html":"{}"},"kv14.2:4.8":{"pli":"Āmantā. ","html":"{}"},"kv14.2:4.9":{"pli":"Mātukucchismiṃ jivhāpaṭilābhāya kammaṃ karotīti? ","html":"{}"},"kv14.2:4.10":{"pli":"Na hevaṃ vattabbe …pe…. ","html":"{}</p>"},"kv14.2:5.1":{"pli":"Mātukucchigatassa pacchā kesā lomā nakhā dantā aṭṭhī uppajjantīti? ","html":"<p data-doxy='heterodox'>{}"},"kv14.2:5.2":{"pli":"Āmantā. ","html":"{}"},"kv14.2:5.3":{"pli":"Mātukucchismiṃ aṭṭhipaṭilābhāya kammaṃ karotīti? ","html":"{}"},"kv14.2:5.4":{"pli":"Na hevaṃ vattabbe …pe…. ","html":"{}</p>"},"kv14.2:6.1":{"pli":"Na vattabbaṃ—","html":"<p data-doxy='orthodox'>{}"},"kv14.2:6.2":{"pli":"“mātukucchigatassa pacchā kesā lomā nakhā dantā aṭṭhī uppajjantī”ti? ","html":"{}"},"kv14.2:6.3":{"pli":"Āmantā. ","html":"{}"},"kv14.2:6.4":{"pli":"Nanu vuttaṃ bhagavatā—","html":"{}</p>"},"kv14.2:7.1":{"pli":"“Paṭhamaṃ kalalaṃ hoti, ","html":"<blockquote class='gatha'><p><span class='verse-line'>{}</span>"},"kv14.2:7.2":{"pli":"kalalā hoti abbudaṃ; ","html":"<span class='verse-line'>{}</span>"},"kv14.2:7.3":{"pli":"Abbudā jāyate pesi, ","html":"<span class='verse-line'>{}</span>"},"kv14.2:7.4":{"pli":"pesi nibbattate ghano; ","html":"<span class='verse-line'>{}</span>"},"kv14.2:7.5":{"pli":"Ghanā pasākhā jāyanti, ","html":"<span class='verse-line'>{}</span>"},"kv14.2:7.6":{"pli":"kesā lomā nakhāpi ca. ","html":"<span class='verse-line'>{}</span></p>"},"kv14.2:8.1":{"pli":"Yañcassa bhuñjati mātā, ","html":"<p><span class='verse-line'>{}</span>"},"kv14.2:8.2":{"pli":"annaṃ pānañca bhojanaṃ; ","html":"<span class='verse-line'>{}</span>"},"kv14.2:8.3":{"pli":"Tena so tattha yāpeti, ","html":"<span class='verse-line'>{}</span>"},"kv14.2:8.4":{"pli":"mātukucchigato naro”ti. ","html":"<span class='verse-line'>{}</span></p></blockquote>"},"kv14.2:9.1":{"pli":"Attheva suttantoti? ","html":"<p>{}"},"kv14.2:9.2":{"pli":"Āmantā. ","html":"{}"},"kv14.2:9.3":{"pli":"Tena hi mātukucchigatassa pacchā kesā lomā nakhā dantā aṭṭhī uppajjantīti. ","html":"{}</p>"},"kv14.2:9.4":{"pli":"Saḷāyatanuppattikathā niṭṭhitā. ","html":"<p class='endsutta'>{}</p></article>"}},"kv14.3":{"kv14.3:0.1":{"pli":"Kathāvatthu ","html":"<article id='kv14.3'><header><ul><li class='division'>{}</li>"},"kv14.3:0.2":{"pli":"Mahāpaṇṇāsaka ","html":"<li>{}</li>"},"kv14.3:0.3":{"pli":"Cuddasamavagga ","html":"<li>{}</li></ul>"},"kv14.3:0.4":{"pli":"Anantarapaccayakathā ","html":"<h1 class='sutta-title'>{}</h1></header>"},"kv14.3:1.1":{"pli":"Cakkhuviññāṇassa anantarā sotaviññāṇaṃ uppajjatīti? ","html":"<p data-doxy='orthodox'>{}"},"kv14.3:1.2":{"pli":"Āmantā. ","html":"{}"},"kv14.3:1.3":{"pli":"Yā cakkhuviññāṇassa uppādāya āvaṭṭanā …pe… paṇidhi, sāva sotaviññāṇassa uppādāya āvaṭṭanā …pe… paṇidhīti? ","html":"{}"},"kv14.3:1.4":{"pli":"Na hevaṃ vattabbe …pe…. ","html":"{}</p>"},"kv14.3:2.1":{"pli":"Cakkhuviññāṇassa anantarā sotaviññāṇaṃ uppajjati, na vattabbaṃ—","html":"<p data-doxy='orthodox'>{}"},"kv14.3:2.2":{"pli":"“yā cakkhuviññāṇassa uppādāya āvaṭṭanā …pe… paṇidhi, sāva sotaviññāṇassa uppādāya āvaṭṭanā …pe… paṇidhī”ti? ","html":"{}"},"kv14.3:2.3":{"pli":"Āmantā. ","html":"{}"},"kv14.3:2.4":{"pli":"Sotaviññāṇaṃ anāvaṭṭentassa uppajjati …pe… appaṇidahantassa uppajjatīti? ","html":"{}"},"kv14.3:2.5":{"pli":"Na hevaṃ vattabbe …pe…. ","html":"{}"},"kv14.3:2.6":{"pli":"Nanu sotaviññāṇaṃ āvaṭṭentassa uppajjati …pe… paṇidahantassa uppajjatīti? ","html":"{}"},"kv14.3:2.7":{"pli":"Āmantā. ","html":"{}"},"kv14.3:2.8":{"pli":"Hañci sotaviññāṇaṃ āvaṭṭentassa uppajjati …pe… paṇidahantassa uppajjati, no ca vata re vattabbe—","html":"{}"},"kv14.3:2.9":{"pli":"“cakkhuviññāṇassa anantarā sotaviññāṇaṃ uppajjatī”ti. ","html":"{}</p>"},"kv14.3:3.1":{"pli":"Cakkhuviññāṇassa anantarā sotaviññāṇaṃ uppajjatīti? ","html":"<p data-doxy='orthodox'>{}"},"kv14.3:3.2":{"pli":"Āmantā. ","html":"{}"},"kv14.3:3.3":{"pli":"Cakkhuviññāṇaṃ rūpanimittaṃ manasikaroto uppajjatīti? ","html":"{}"},"kv14.3:3.4":{"pli":"Āmantā. ","html":"{}"},"kv14.3:3.5":{"pli":"Sotaviññāṇaṃ rūpanimittaṃ manasikaroto uppajjatīti? ","html":"{}"},"kv14.3:3.6":{"pli":"Na hevaṃ vattabbe …pe…. ","html":"{}</p>"},"kv14.3:4.1":{"pli":"Cakkhuviññāṇaṃ rūpārammaṇaññeva na aññārammaṇanti? ","html":"<p data-doxy='orthodox'>{}"},"kv14.3:4.2":{"pli":"Āmantā. ","html":"{}"},"kv14.3:4.3":{"pli":"Sotaviññāṇaṃ rūpārammaṇaññeva na aññārammaṇanti? ","html":"{}"},"kv14.3:4.4":{"pli":"Na hevaṃ vattabbe …pe…. ","html":"{}</p>"},"kv14.3:5.1":{"pli":"Cakkhuñca paṭicca rūpe ca uppajjati cakkhuviññāṇanti? ","html":"<p data-doxy='orthodox'>{}"},"kv14.3:5.2":{"pli":"Āmantā. ","html":"{}"},"kv14.3:5.3":{"pli":"Cakkhuñca paṭicca rūpe ca uppajjati sotaviññāṇanti? ","html":"{}"},"kv14.3:5.4":{"pli":"Na hevaṃ vattabbe …pe…. ","html":"{}</p>"},"kv14.3:6.1":{"pli":"Cakkhuñca paṭicca rūpe ca uppajjati sotaviññāṇanti? ","html":"<p data-doxy='orthodox'>{}"},"kv14.3:6.2":{"pli":"Āmantā. ","html":"{}"},"kv14.3:6.3":{"pli":"“Cakkhuñca paṭicca rūpe ca uppajjati sotaviññāṇan”ti—","html":"{}"},"kv14.3:6.4":{"pli":"attheva suttantoti? ","html":"{}"},"kv14.3:6.5":{"pli":"Natthi. ","html":"{}"},"kv14.3:6.6":{"pli":"“Cakkhuñca paṭicca rūpe ca uppajjati cakkhuviññāṇan”ti—","html":"{}"},"kv14.3:6.7":{"pli":"attheva suttantoti? ","html":"{}"},"kv14.3:6.8":{"pli":"Āmantā. ","html":"{}"},"kv14.3:6.9":{"pli":"Hañci “cakkhuñca paṭicca rūpe ca uppajjati cakkhuviññāṇan”ti—","html":"{}"},"kv14.3:6.10":{"pli":"attheva suttanto, no ca vata re vattabbe—","html":"{}"},"kv14.3:6.11":{"pli":"“cakkhuñca paṭicca rūpe ca uppajjati sotaviññāṇan”ti. ","html":"{}</p>"},"kv14.3:7.1":{"pli":"Cakkhuviññāṇassa anantarā sotaviññāṇaṃ uppajjatīti? ","html":"<p data-doxy='orthodox'>{}"},"kv14.3:7.2":{"pli":"Āmantā. ","html":"{}"},"kv14.3:7.3":{"pli":"Taññeva cakkhuviññāṇaṃ taṃ sotaviññāṇanti? ","html":"{}"},"kv14.3:7.4":{"pli":"Na hevaṃ vattabbe …pe…. ","html":"{}</p>"},"kv14.3:8.1":{"pli":"Sotaviññāṇassa anantarā ghānaviññāṇaṃ uppajjati …pe… ","html":"<p data-doxy='orthodox'>{}"},"kv14.3:8.2":{"pli":"ghānaviññāṇassa anantarā jivhāviññāṇaṃ uppajjati …pe… ","html":"{}"},"kv14.3:8.3":{"pli":"jivhāviññāṇassa anantarā kāyaviññāṇaṃ uppajjatīti? ","html":"{}"},"kv14.3:8.4":{"pli":"Āmantā. ","html":"{}"},"kv14.3:8.5":{"pli":"Yā jivhāviññāṇassa uppādāya āvaṭṭanā …pe… paṇidhi, sāva kāyaviññāṇassa uppādāya āvaṭṭanā …pe… paṇidhīti? ","html":"{}"},"kv14.3:8.6":{"pli":"Na hevaṃ vattabbe …pe… ","html":"{}"},"kv14.3:8.7":{"pli":"jivhāviññāṇassa anantarā kāyaviññāṇaṃ uppajjati, na vattabbaṃ—","html":"{}"},"kv14.3:8.8":{"pli":"“yā jivhāviññāṇassa uppādāya āvaṭṭanā …pe… paṇidhi, sāva kāyaviññāṇassa uppādāya āvaṭṭanā …pe… paṇidhī”ti? ","html":"{}"},"kv14.3:8.9":{"pli":"Āmantā. ","html":"{}"},"kv14.3:8.10":{"pli":"Kāyaviññāṇaṃ anāvaṭṭentassa uppajjati …pe… appaṇidahantassa uppajjatīti? ","html":"{}"},"kv14.3:8.11":{"pli":"Na hevaṃ vattabbe …pe… ","html":"{}"},"kv14.3:8.12":{"pli":"nanu kāyaviññāṇaṃ āvaṭṭentassa uppajjati …pe… paṇidahantassa uppajjatīti? ","html":"{}"},"kv14.3:8.13":{"pli":"Āmantā. ","html":"{}"},"kv14.3:8.14":{"pli":"Hañci kāyaviññāṇaṃ āvaṭṭentassa uppajjati …pe… paṇidahantassa uppajjati, no ca vata re vattabbe—","html":"{}"},"kv14.3:8.15":{"pli":"“jivhāviññāṇassa anantarā kāyaviññāṇaṃ uppajjatī”ti. ","html":"{}</p>"},"kv14.3:9.1":{"pli":"Jivhāviññāṇassa anantarā kāyaviññāṇaṃ uppajjatīti? ","html":"<p data-doxy='orthodox'>{}"},"kv14.3:9.2":{"pli":"Āmantā. ","html":"{}"},"kv14.3:9.3":{"pli":"Jivhāviññāṇaṃ rasanimittaṃ manasikaroto uppajjatīti? ","html":"{}"},"kv14.3:9.4":{"pli":"Āmantā. ","html":"{}"},"kv14.3:9.5":{"pli":"Kāyaviññāṇaṃ rasanimittaṃ manasikaroto uppajjatīti? ","html":"{}"},"kv14.3:9.6":{"pli":"Na hevaṃ vattabbe …pe…. ","html":"{}</p>"},"kv14.3:10.1":{"pli":"Jivhāviññāṇaṃ rasārammaṇaññeva na aññārammaṇanti? ","html":"<p data-doxy='orthodox'>{}"},"kv14.3:10.2":{"pli":"Āmantā. ","html":"{}"},"kv14.3:10.3":{"pli":"Kāyaviññāṇaṃ rasārammaṇaññeva na aññārammaṇanti? ","html":"{}"},"kv14.3:10.4":{"pli":"Na hevaṃ vattabbe …pe…. ","html":"{}</p>"},"kv14.3:11.1":{"pli":"Jivhañca paṭicca rase ca uppajjati jivhāviññāṇanti? ","html":"<p data-doxy='orthodox'>{}"},"kv14.3:11.2":{"pli":"Āmantā. ","html":"{}"},"kv14.3:11.3":{"pli":"Jivhañca paṭicca rase ca uppajjati kāyaviññāṇanti? ","html":"{}"},"kv14.3:11.4":{"pli":"Na hevaṃ vattabbe …pe…. ","html":"{}</p>"},"kv14.3:12.1":{"pli":"Jivhañca paṭicca rase ca uppajjati kāyaviññāṇanti? ","html":"<p data-doxy='orthodox'>{}"},"kv14.3:12.2":{"pli":"Āmantā. ","html":"{}"},"kv14.3:12.3":{"pli":"“Jivhañca paṭicca rase ca uppajjati kāyaviññāṇan”ti—","html":"{}"},"kv14.3:12.4":{"pli":"attheva suttantoti? ","html":"{}"},"kv14.3:12.5":{"pli":"Natthi. ","html":"{}"},"kv14.3:12.6":{"pli":"“Jivhañca paṭicca rase ca uppajjati jivhāviññāṇan”ti—","html":"{}"},"kv14.3:12.7":{"pli":"attheva suttantoti? ","html":"{}"},"kv14.3:12.8":{"pli":"Āmantā. ","html":"{}"},"kv14.3:12.9":{"pli":"Hañci “jivhañca paṭicca rase ca uppajjati jivhāviññāṇan”ti—","html":"{}"},"kv14.3:12.10":{"pli":"attheva suttantoti, no ca vata re vattabbe—","html":"{}"},"kv14.3:12.11":{"pli":"“jivhañca paṭicca rase ca uppajjati kāyaviññāṇan”ti. ","html":"{}</p>"},"kv14.3:13.1":{"pli":"Jivhāviññāṇassa anantarā kāyaviññāṇaṃ uppajjatīti? ","html":"<p data-doxy='orthodox'>{}"},"kv14.3:13.2":{"pli":"Āmantā. ","html":"{}"},"kv14.3:13.3":{"pli":"Taññeva jivhāviññāṇaṃ taṃ kāyaviññāṇanti? ","html":"{}"},"kv14.3:13.4":{"pli":"Na hevaṃ vattabbe …pe…. ","html":"{}</p>"},"kv14.3:14.1":{"pli":"Na vattabbaṃ—","html":"<p data-doxy='heterodox'>{}"},"kv14.3:14.2":{"pli":"“pañcaviññāṇā aññamaññassa samanantarā uppajjantī”ti? ","html":"{}"},"kv14.3:14.3":{"pli":"Āmantā. ","html":"{}"},"kv14.3:14.4":{"pli":"Nanu atthi koci naccati gāyati vādeti, rūpañca passati, saddañca suṇāti, gandhañca ghāyati, rasañca sāyati, phoṭṭhabbañca phusatīti? ","html":"{}"},"kv14.3:14.5":{"pli":"Āmantā. ","html":"{}"},"kv14.3:14.6":{"pli":"Hañci atthi koci naccati gāyati vādeti, rūpañca passati, saddañca suṇāti, gandhañca ghāyati, rasañca sāyati, phoṭṭhabbañca phusati, tena vata re vattabbe—","html":"{}"},"kv14.3:14.7":{"pli":"“pañcaviññāṇā aññamaññassa samanantarā uppajjantī”ti. ","html":"{}</p>"},"kv14.3:14.8":{"pli":"Anantarapaccayakathā niṭṭhitā. ","html":"<p class='endsutta'>{}</p></article>"}},"kv14.4":{"kv14.4:0.1":{"pli":"Kathāvatthu ","html":"<article id='kv14.4'><header><ul><li class='division'>{}</li>"},"kv14.4:0.2":{"pli":"Mahāpaṇṇāsaka ","html":"<li>{}</li>"},"kv14.4:0.3":{"pli":"Cuddasamavagga ","html":"<li>{}</li></ul>"},"kv14.4:0.4":{"pli":"Ariyarūpakathā ","html":"<h1 class='sutta-title'>{}</h1></header>"},"kv14.4:1.1":{"pli":"Ariyarūpaṃ mahābhūtānaṃ upādāyāti? ","html":"<p data-doxy='orthodox'>{}"},"kv14.4:1.2":{"pli":"Āmantā. ","html":"{}"},"kv14.4:1.3":{"pli":"Ariyarūpaṃ kusalanti? ","html":"{}"},"kv14.4:1.4":{"pli":"Āmantā. ","html":"{}"},"kv14.4:1.5":{"pli":"Mahābhūtā kusalāti? ","html":"{}"},"kv14.4:1.6":{"pli":"Na hevaṃ vattabbe …pe… ","html":"{}"},"kv14.4:1.7":{"pli":"mahābhūtā abyākatāti? ","html":"{}"},"kv14.4:1.8":{"pli":"Āmantā. ","html":"{}"},"kv14.4:1.9":{"pli":"Ariyarūpaṃ abyākatanti? ","html":"{}"},"kv14.4:1.10":{"pli":"Na hevaṃ vattabbe …pe… ","html":"{}"},"kv14.4:1.11":{"pli":"ariyarūpaṃ mahābhūtānaṃ upādāyāti? ","html":"{}"},"kv14.4:1.12":{"pli":"Āmantā. ","html":"{}"},"kv14.4:1.13":{"pli":"Ariyarūpaṃ anāsavaṃ asaṃyojaniyaṃ aganthaniyaṃ anoghaniyaṃ ayoganiyaṃ anīvaraṇiyaṃ aparāmaṭṭhaṃ anupādāniyaṃ asaṅkilesiyanti? ","html":"{}"},"kv14.4:1.14":{"pli":"Āmantā. ","html":"{}"},"kv14.4:1.15":{"pli":"Mahābhūtā anāsavā …pe… asaṅkilesiyāti? ","html":"{}"},"kv14.4:1.16":{"pli":"Na hevaṃ vattabbe …pe… ","html":"{}"},"kv14.4:1.17":{"pli":"mahābhūtā sāsavā saṃyojaniyā …pe… saṅkilesiyāti? ","html":"{}"},"kv14.4:1.18":{"pli":"Āmantā. ","html":"{}"},"kv14.4:1.19":{"pli":"Ariyarūpaṃ sāsavaṃ saṃyojaniyaṃ …pe… saṅkilesiyanti? ","html":"{}"},"kv14.4:1.20":{"pli":"Na hevaṃ vattabbe …pe…. ","html":"{}</p>"},"kv14.4:2.1":{"pli":"Na vattabbaṃ—","html":"<p data-doxy='heterodox'>{}"},"kv14.4:2.2":{"pli":"“ariyarūpaṃ mahābhūtānaṃ upādāyā”ti? ","html":"{}"},"kv14.4:2.3":{"pli":"Āmantā. ","html":"{}"},"kv14.4:2.4":{"pli":"Nanu vuttaṃ bhagavatā—","html":"{}"},"kv14.4:2.5":{"pli":"“yaṃ kiñci, bhikkhave, rūpaṃ cattāri mahābhūtāni catunnañca mahābhūtānaṃ upādāyarūpan”ti. ","html":"{}"},"kv14.4:2.6":{"pli":"Attheva suttantoti? ","html":"{}"},"kv14.4:2.7":{"pli":"Āmantā. ","html":"{}"},"kv14.4:2.8":{"pli":"Tena hi ariyarūpaṃ mahābhūtānaṃ upādāyāti. ","html":"{}</p>"},"kv14.4:2.9":{"pli":"Ariyarūpakathā niṭṭhitā. ","html":"<p class='endsutta'>{}</p></article>"}},"kv14.5":{"kv14.5:0.1":{"pli":"Kathāvatthu ","html":"<article id='kv14.5'><header><ul><li class='division'>{}</li>"},"kv14.5:0.2":{"pli":"Mahāpaṇṇāsaka ","html":"<li>{}</li>"},"kv14.5:0.3":{"pli":"Cuddasamavagga ","html":"<li>{}</li></ul>"},"kv14.5:0.4":{"pli":"Aññoanusayotikathā ","html":"<h1 class='sutta-title'>{}</h1></header>"},"kv14.5:1.1":{"pli":"Añño kāmarāgānusayo aññaṃ kāmarāgapariyuṭṭhānanti? ","html":"<p data-doxy='orthodox'>{}"},"kv14.5:1.2":{"pli":"Āmantā. ","html":"{}"},"kv14.5:1.3":{"pli":"Añño kāmarāgo aññaṃ kāmarāgapariyuṭṭhānanti? ","html":"{}"},"kv14.5:1.4":{"pli":"Na hevaṃ vattabbe …pe… ","html":"{}"},"kv14.5:1.5":{"pli":"sveva kāmarāgo taṃ kāmarāgapariyuṭṭhānanti? ","html":"{}"},"kv14.5:1.6":{"pli":"Āmantā. ","html":"{}"},"kv14.5:1.7":{"pli":"Sveva kāmarāgānusayo taṃ kāmarāgapariyuṭṭhānanti? ","html":"{}"},"kv14.5:1.8":{"pli":"Na hevaṃ vattabbe …pe…. ","html":"{}</p>"},"kv14.5:2.1":{"pli":"Añño paṭighānusayo aññaṃ paṭighapariyuṭṭhānanti? ","html":"<p data-doxy='orthodox'>{}"},"kv14.5:2.2":{"pli":"Āmantā. ","html":"{}"},"kv14.5:2.3":{"pli":"Aññaṃ paṭighaṃ aññaṃ paṭighapariyuṭṭhānanti? ","html":"{}"},"kv14.5:2.4":{"pli":"Na hevaṃ vattabbe …pe… ","html":"{}"},"kv14.5:2.5":{"pli":"taññeva paṭighaṃ taṃ paṭighapariyuṭṭhānanti? ","html":"{}"},"kv14.5:2.6":{"pli":"Āmantā. ","html":"{}"},"kv14.5:2.7":{"pli":"Sveva paṭighānusayo taṃ paṭighapariyuṭṭhānanti? ","html":"{}"},"kv14.5:2.8":{"pli":"Na hevaṃ vattabbe …pe…. ","html":"{}</p>"},"kv14.5:3.1":{"pli":"Añño mānānusayo aññaṃ mānapariyuṭṭhānanti? ","html":"<p data-doxy='orthodox'>{}"},"kv14.5:3.2":{"pli":"Āmantā. ","html":"{}"},"kv14.5:3.3":{"pli":"Añño māno aññaṃ mānapariyuṭṭhānanti? ","html":"{}"},"kv14.5:3.4":{"pli":"Na hevaṃ vattabbe …pe… ","html":"{}"},"kv14.5:3.5":{"pli":"sveva māno taṃ mānapariyuṭṭhānanti? ","html":"{}"},"kv14.5:3.6":{"pli":"Āmantā. ","html":"{}"},"kv14.5:3.7":{"pli":"Sveva mānānusayo taṃ mānapariyuṭṭhānanti? ","html":"{}"},"kv14.5:3.8":{"pli":"Na hevaṃ vattabbe …pe…. ","html":"{}</p>"},"kv14.5:4.1":{"pli":"Añño diṭṭhānusayo aññaṃ diṭṭhipariyuṭṭhānanti? ","html":"<p data-doxy='orthodox'>{}"},"kv14.5:4.2":{"pli":"Āmantā. ","html":"{}"},"kv14.5:4.3":{"pli":"Aññā diṭṭhi aññaṃ diṭṭhipariyuṭṭhānanti? ","html":"{}"},"kv14.5:4.4":{"pli":"Na hevaṃ vattabbe …pe… ","html":"{}"},"kv14.5:4.5":{"pli":"sāva diṭṭhi taṃ diṭṭhipariyuṭṭhānanti? ","html":"{}"},"kv14.5:4.6":{"pli":"Āmantā. ","html":"{}"},"kv14.5:4.7":{"pli":"Sveva diṭṭhānusayo taṃ diṭṭhipariyuṭṭhānanti? ","html":"{}"},"kv14.5:4.8":{"pli":"Na hevaṃ vattabbe …pe…. ","html":"{}</p>"},"kv14.5:5.1":{"pli":"Añño vicikicchānusayo aññaṃ vicikicchāpariyuṭṭhānanti? ","html":"<p data-doxy='orthodox'>{}"},"kv14.5:5.2":{"pli":"Āmantā. ","html":"{}"},"kv14.5:5.3":{"pli":"Aññā vicikicchā aññaṃ vicikicchāpariyuṭṭhānanti? ","html":"{}"},"kv14.5:5.4":{"pli":"Na hevaṃ vattabbe …pe… ","html":"{}"},"kv14.5:5.5":{"pli":"sāva vicikicchā taṃ vicikicchāpariyuṭṭhānanti? ","html":"{}"},"kv14.5:5.6":{"pli":"Āmantā. ","html":"{}"},"kv14.5:5.7":{"pli":"Sveva vicikicchānusayo taṃ vicikicchāpariyuṭṭhānanti? ","html":"{}"},"kv14.5:5.8":{"pli":"Na hevaṃ vattabbe …pe…. ","html":"{}</p>"},"kv14.5:6.1":{"pli":"Añño bhavarāgānusayo aññaṃ bhavarāgapariyuṭṭhānanti? ","html":"<p data-doxy='orthodox'>{}"},"kv14.5:6.2":{"pli":"Āmantā. ","html":"{}"},"kv14.5:6.3":{"pli":"Añño bhavarāgo aññaṃ bhavarāgapariyuṭṭhānanti? ","html":"{}"},"kv14.5:6.4":{"pli":"Na hevaṃ vattabbe …pe… ","html":"{}"},"kv14.5:6.5":{"pli":"sveva bhavarāgo taṃ bhavarāgapariyuṭṭhānanti? ","html":"{}"},"kv14.5:6.6":{"pli":"Āmantā. ","html":"{}"},"kv14.5:6.7":{"pli":"Sveva bhavarāgānusayo taṃ bhavarāgapariyuṭṭhānanti? ","html":"{}"},"kv14.5:6.8":{"pli":"Na hevaṃ vattabbe …pe…. ","html":"{}</p>"},"kv14.5:7.1":{"pli":"Añño avijjānusayo aññaṃ avijjāpariyuṭṭhānanti? ","html":"<p data-doxy='orthodox'>{}"},"kv14.5:7.2":{"pli":"Āmantā. ","html":"{}"},"kv14.5:7.3":{"pli":"Aññā avijjā aññaṃ avijjāpariyuṭṭhānanti? ","html":"{}"},"kv14.5:7.4":{"pli":"Na hevaṃ vattabbe …pe… ","html":"{}"},"kv14.5:7.5":{"pli":"sāva avijjā taṃ avijjāpariyuṭṭhānanti? ","html":"{}"},"kv14.5:7.6":{"pli":"Āmantā. ","html":"{}"},"kv14.5:7.7":{"pli":"Sveva avijjānusayo taṃ avijjāpariyuṭṭhānanti? ","html":"{}"},"kv14.5:7.8":{"pli":"Na hevaṃ vattabbe …pe…. ","html":"{}</p>"},"kv14.5:8.1":{"pli":"Na vattabbaṃ—","html":"<p data-doxy='heterodox'>{}"},"kv14.5:8.2":{"pli":"“añño anusayo aññaṃ pariyuṭṭhānan”ti? ","html":"{}"},"kv14.5:8.3":{"pli":"Āmantā. ","html":"{}"},"kv14.5:8.4":{"pli":"Puthujjano kusalābyākate citte vattamāne “sānusayo”ti vattabboti? ","html":"{}"},"kv14.5:8.5":{"pli":"Āmantā. ","html":"{}"},"kv14.5:8.6":{"pli":"“Pariyuṭṭhito”ti vattabboti? ","html":"{}"},"kv14.5:8.7":{"pli":"Na hevaṃ vattabbe. ","html":"{}"},"kv14.5:8.8":{"pli":"Tena hi añño anusayo aññaṃ pariyuṭṭhānanti. ","html":"{}"},"kv14.5:8.9":{"pli":"Puthujjano kusalābyākate citte vattamāne “sarāgo”ti vattabboti? ","html":"{}"},"kv14.5:8.10":{"pli":"Āmantā. ","html":"{}"},"kv14.5:8.11":{"pli":"“Pariyuṭṭhito”ti vattabboti? ","html":"{}"},"kv14.5:8.12":{"pli":"Na hevaṃ vattabbe. ","html":"{}"},"kv14.5:8.13":{"pli":"Tena hi añño rāgo aññaṃ pariyuṭṭhānanti. ","html":"{}</p>"},"kv14.5:8.14":{"pli":"Añño anusayotikathā niṭṭhitā. ","html":"<p class='endsutta'>{}</p></article>"}},"kv14.6":{"kv14.6:0.1":{"pli":"Kathāvatthu ","html":"<article id='kv14.6'><header><ul><li class='division'>{}</li>"},"kv14.6:0.2":{"pli":"Mahāpaṇṇāsaka ","html":"<li>{}</li>"},"kv14.6:0.3":{"pli":"Cuddasamavagga ","html":"<li>{}</li></ul>"},"kv14.6:0.4":{"pli":"Pariyuṭṭhānaṃcittavippayuttantikathā ","html":"<h1 class='sutta-title'>{}</h1></header>"},"kv14.6:1.1":{"pli":"Pariyuṭṭhānaṃ cittavippayuttanti? ","html":"<p data-doxy='orthodox'>{}"},"kv14.6:1.2":{"pli":"Āmantā. ","html":"{}"},"kv14.6:1.3":{"pli":"Rūpaṃ nibbānaṃ cakkhāyatanaṃ …pe… ","html":"{}"},"kv14.6:1.4":{"pli":"phoṭṭhabbāyatananti? ","html":"{}"},"kv14.6:1.5":{"pli":"Na hevaṃ vattabbe …pe… ","html":"{}"},"kv14.6:1.6":{"pli":"pariyuṭṭhānaṃ cittavippayuttanti? ","html":"{}"},"kv14.6:1.7":{"pli":"Āmantā. ","html":"{}"},"kv14.6:1.8":{"pli":"Natthi sarāgaṃ cittaṃ sadosaṃ cittaṃ samohaṃ cittaṃ …pe… ","html":"{}"},"kv14.6:1.9":{"pli":"akusalaṃ cittaṃ saṅkiliṭṭhaṃ cittanti? ","html":"{}"},"kv14.6:1.10":{"pli":"Na hevaṃ vattabbe …pe… ","html":"{}"},"kv14.6:1.11":{"pli":"nanu atthi sarāgaṃ cittaṃ sadosaṃ cittaṃ samohaṃ cittaṃ …pe… ","html":"{}"},"kv14.6:1.12":{"pli":"akusalaṃ cittaṃ saṅkiliṭṭhaṃ cittanti? ","html":"{}"},"kv14.6:1.13":{"pli":"Āmantā. ","html":"{}"},"kv14.6:1.14":{"pli":"Hañci atthi sarāgaṃ cittaṃ sadosaṃ cittaṃ samohaṃ cittaṃ …pe… ","html":"{}"},"kv14.6:1.15":{"pli":"akusalaṃ cittaṃ saṅkiliṭṭhaṃ cittaṃ, no ca vata re vattabbe—","html":"{}"},"kv14.6:1.16":{"pli":"“pariyuṭṭhānaṃ cittavippayuttan”ti. ","html":"{}</p>"},"kv14.6:1.17":{"pli":"Pariyuṭṭhānaṃ cittavippayuttantikathā niṭṭhitā. ","html":"<p class='endsutta'>{}</p></article>"}},"kv14.7":{"kv14.7:0.1":{"pli":"Kathāvatthu ","html":"<article id='kv14.7'><header><ul><li class='division'>{}</li>"},"kv14.7:0.2":{"pli":"Mahāpaṇṇāsaka ","html":"<li>{}</li>"},"kv14.7:0.3":{"pli":"Cuddasamavagga ","html":"<li>{}</li></ul>"},"kv14.7:0.4":{"pli":"Pariyāpannakathā ","html":"<h1 class='sutta-title'>{}</h1></header>"},"kv14.7:1.1":{"pli":"Rūparāgo rūpadhātuṃ anuseti, rūpadhātupariyāpannoti? ","html":"<p data-doxy='orthodox'>{}"},"kv14.7:1.2":{"pli":"Āmantā. ","html":"{}"},"kv14.7:1.3":{"pli":"Samāpattesiyo upapattesiyo diṭṭhadhammasukhavihāro, samāpattesiyena cittena upapattesiyena cittena diṭṭhadhammasukhavihārena cittena sahagato sahajāto saṃsaṭṭho sampayutto ekuppādo ekanirodho ekavatthuko ekārammaṇoti? ","html":"{}"},"kv14.7:1.4":{"pli":"Na hevaṃ vattabbe …pe… ","html":"{}"},"kv14.7:1.5":{"pli":"nanu na samāpattesiyo na upapattesiyo na diṭṭhadhammasukhavihāro, na samāpattesiyena cittena na upapattesiyena cittena na diṭṭhadhammasukhavihārena cittena sahagato sahajāto saṃsaṭṭho sampayutto ekuppādo ekanirodho ekavatthuko ekārammaṇoti? ","html":"{}"},"kv14.7:1.6":{"pli":"Āmantā. ","html":"{}"},"kv14.7:1.7":{"pli":"Hañci na samāpattesiyo na upapattesiyo na diṭṭhadhammasukhavihāro …pe… ekārammaṇo, no ca vata re vattabbe—","html":"{}"},"kv14.7:1.8":{"pli":"“rūparāgo rūpadhātuṃ anuseti, rūpadhātupariyāpanno”ti …pe…. ","html":"{}</p>"},"kv14.7:2.1":{"pli":"Rūparāgo rūpadhātuṃ anuseti, rūpadhātupariyāpannoti? ","html":"<p data-doxy='orthodox'>{}"},"kv14.7:2.2":{"pli":"Āmantā. ","html":"{}"},"kv14.7:2.3":{"pli":"Saddarāgo saddadhātuṃ anuseti, saddadhātupariyāpannoti? ","html":"{}"},"kv14.7:2.4":{"pli":"Na hevaṃ vattabbe …pe… ","html":"{}"},"kv14.7:2.5":{"pli":"rūparāgo rūpadhātuṃ anuseti, rūpadhātupariyāpannoti? ","html":"{}"},"kv14.7:2.6":{"pli":"Āmantā. ","html":"{}"},"kv14.7:2.7":{"pli":"Gandharāgo …pe… ","html":"{}"},"kv14.7:2.8":{"pli":"rasarāgo …pe… ","html":"{}"},"kv14.7:2.9":{"pli":"phoṭṭhabbarāgo phoṭṭhabbadhātuṃ anuseti, phoṭṭhabbadhātupariyāpannoti? ","html":"{}"},"kv14.7:2.10":{"pli":"Na hevaṃ vattabbe …pe…. ","html":"{}</p>"},"kv14.7:3.1":{"pli":"Saddarāgo saddadhātuṃ anuseti, na vattabbaṃ—","html":"<p data-doxy='orthodox'>{}"},"kv14.7:3.2":{"pli":"“saddadhātupariyāpanno”ti? ","html":"{}"},"kv14.7:3.3":{"pli":"Āmantā. ","html":"{}"},"kv14.7:3.4":{"pli":"Rūparāgo rūpadhātuṃ anuseti, na vattabbaṃ—","html":"{}"},"kv14.7:3.5":{"pli":"“rūpadhātupariyāpanno”ti? ","html":"{}"},"kv14.7:3.6":{"pli":"Na hevaṃ vattabbe …pe… ","html":"{}"},"kv14.7:3.7":{"pli":"gandharāgo …pe… ","html":"{}"},"kv14.7:3.8":{"pli":"rasarāgo …pe… ","html":"{}"},"kv14.7:3.9":{"pli":"phoṭṭhabbarāgo phoṭṭhabbadhātuṃ anuseti, na vattabbaṃ—","html":"{}"},"kv14.7:3.10":{"pli":"“phoṭṭhabbadhātupariyāpanno”ti? ","html":"{}"},"kv14.7:3.11":{"pli":"Āmantā. ","html":"{}"},"kv14.7:3.12":{"pli":"Rūparāgo rūpadhātuṃ anuseti, na vattabbaṃ—","html":"{}"},"kv14.7:3.13":{"pli":"“rūpadhātupariyāpanno”ti? ","html":"{}"},"kv14.7:3.14":{"pli":"Na hevaṃ vattabbe …pe…. ","html":"{}</p>"},"kv14.7:4.1":{"pli":"Arūparāgo arūpadhātuṃ anuseti, arūpadhātupariyāpannoti? ","html":"<p data-doxy='orthodox'>{}"},"kv14.7:4.2":{"pli":"Āmantā. ","html":"{}"},"kv14.7:4.3":{"pli":"Samāpattesiyo upapattesiyo diṭṭhadhammasukhavihāro, samāpattesiyena cittena upapattesiyena cittena diṭṭhadhammasukhavihārena cittena sahagato sahajāto saṃsaṭṭho sampayutto ekuppādo ekanirodho ekavatthuko ekārammaṇoti? ","html":"{}"},"kv14.7:4.4":{"pli":"Na hevaṃ vattabbe …pe…. ","html":"{}"},"kv14.7:4.5":{"pli":"Nanu na samāpattesiyo na upapattesiyo na diṭṭhadhammasukhavihāro, na samāpattesiyena cittena …pe… ekārammaṇoti? ","html":"{}"},"kv14.7:4.6":{"pli":"Āmantā. ","html":"{}"},"kv14.7:4.7":{"pli":"Hañci na samāpattesiyo na upapattesiyo …pe… ","html":"{}"},"kv14.7:4.8":{"pli":"ekārammaṇo, no ca vata re vattabbe—","html":"{}"},"kv14.7:4.9":{"pli":"“arūparāgo arūpadhātuṃ anuseti, arūpadhātupariyāpanno”ti. ","html":"{}</p>"},"kv14.7:5.1":{"pli":"Arūparāgo arūpadhātuṃ anuseti, arūpadhātupariyāpannoti? ","html":"<p data-doxy='orthodox'>{}"},"kv14.7:5.2":{"pli":"Āmantā. ","html":"{}"},"kv14.7:5.3":{"pli":"Saddarāgo saddadhātuṃ anuseti, saddadhātupariyāpannoti? ","html":"{}"},"kv14.7:5.4":{"pli":"Na hevaṃ vattabbe …pe… ","html":"{}"},"kv14.7:5.5":{"pli":"arūparāgo arūpadhātuṃ anuseti, arūpadhātupariyāpannoti? ","html":"{}"},"kv14.7:5.6":{"pli":"Āmantā. ","html":"{}"},"kv14.7:5.7":{"pli":"Gandharāgo …pe… ","html":"{}"},"kv14.7:5.8":{"pli":"rasarāgo …pe… ","html":"{}"},"kv14.7:5.9":{"pli":"phoṭṭhabbarāgo phoṭṭhabbadhātuṃ anuseti, phoṭṭhabbadhātupariyāpannoti? ","html":"{}"},"kv14.7:5.10":{"pli":"Na hevaṃ vattabbe …pe…. ","html":"{}</p>"},"kv14.7:6.1":{"pli":"Saddarāgo saddadhātuṃ anuseti, na vattabbaṃ—","html":"<p data-doxy='orthodox'>{}"},"kv14.7:6.2":{"pli":"“saddadhātupariyāpanno”ti? ","html":"{}"},"kv14.7:6.3":{"pli":"Āmantā. ","html":"{}"},"kv14.7:6.4":{"pli":"Arūparāgo arūpadhātuṃ anuseti, na vattabbaṃ—","html":"{}"},"kv14.7:6.5":{"pli":"“arūpadhātupariyāpanno”ti, na hevaṃ vattabbe …pe… ","html":"{}"},"kv14.7:6.6":{"pli":"gandharāgo …pe… ","html":"{}"},"kv14.7:6.7":{"pli":"rasarāgo …pe… ","html":"{}"},"kv14.7:6.8":{"pli":"phoṭṭhabbarāgo phoṭṭhabbadhātuṃ anuseti, na vattabbaṃ—","html":"{}"},"kv14.7:6.9":{"pli":"“phoṭṭhabbadhātupariyāpanno”ti? ","html":"{}"},"kv14.7:6.10":{"pli":"Āmantā. ","html":"{}"},"kv14.7:6.11":{"pli":"Arūparāgo arūpadhātuṃ anuseti, na vattabbaṃ—","html":"{}"},"kv14.7:6.12":{"pli":"“arūpadhātupariyāpanno”ti? ","html":"{}"},"kv14.7:6.13":{"pli":"Na hevaṃ vattabbe …pe…. ","html":"{}</p>"},"kv14.7:7.1":{"pli":"Na vattabbaṃ—","html":"<p data-doxy='heterodox'>{}"},"kv14.7:7.2":{"pli":"“rūparāgo rūpadhātuṃ anuseti rūpadhātupariyāpanno, arūparāgo arūpadhātuṃ anuseti arūpadhātupariyāpanno”ti? ","html":"{}"},"kv14.7:7.3":{"pli":"Āmantā. ","html":"{}"},"kv14.7:7.4":{"pli":"Nanu kāmarāgo kāmadhātuṃ anuseti, kāmadhātupariyāpannoti? ","html":"{}"},"kv14.7:7.5":{"pli":"Āmantā. ","html":"{}"},"kv14.7:7.6":{"pli":"Hañci kāmarāgo kāmadhātuṃ anuseti kāmadhātupariyāpanno, tena vata re vattabbe—","html":"{}"},"kv14.7:7.7":{"pli":"“rūparāgo rūpadhātuṃ anuseti rūpadhātupariyāpanno, arūparāgo arūpadhātuṃ anuseti arūpadhātupariyāpanno”ti. ","html":"{}</p>"},"kv14.7:7.8":{"pli":"Pariyāpannakathā niṭṭhitā. ","html":"<p class='endsutta'>{}</p></article>"}},"kv14.8":{"kv14.8:0.1":{"pli":"Kathāvatthu ","html":"<article id='kv14.8'><header><ul><li class='division'>{}</li>"},"kv14.8:0.2":{"pli":"Mahāpaṇṇāsaka ","html":"<li>{}</li>"},"kv14.8:0.3":{"pli":"Cuddasamavagga ","html":"<li>{}</li></ul>"},"kv14.8:0.4":{"pli":"Abyākatakathā ","html":"<h1 class='sutta-title'>{}</h1></header>"},"kv14.8:1.1":{"pli":"Diṭṭhigataṃ abyākatanti? ","html":"<p data-doxy='orthodox'>{}"},"kv14.8:1.2":{"pli":"Āmantā. ","html":"{}"},"kv14.8:1.3":{"pli":"Vipākābyākataṃ kiriyābyākataṃ rūpaṃ nibbānaṃ cakkhāyatanaṃ …pe… ","html":"{}"},"kv14.8:1.4":{"pli":"phoṭṭhabbāyatananti? ","html":"{}"},"kv14.8:1.5":{"pli":"Na hevaṃ vattabbe …pe… ","html":"{}"},"kv14.8:1.6":{"pli":"diṭṭhigataṃ abyākatanti? ","html":"{}"},"kv14.8:1.7":{"pli":"Āmantā. ","html":"{}"},"kv14.8:1.8":{"pli":"Diṭṭhigatasampayutto phasso abyākatoti? ","html":"{}"},"kv14.8:1.9":{"pli":"Na hevaṃ vattabbe …pe… ","html":"{}"},"kv14.8:1.10":{"pli":"diṭṭhigataṃ abyākatanti? ","html":"{}"},"kv14.8:1.11":{"pli":"Āmantā. ","html":"{}"},"kv14.8:1.12":{"pli":"Diṭṭhigatasampayuttā vedanā …pe… ","html":"{}"},"kv14.8:1.13":{"pli":"saññā …pe… ","html":"{}"},"kv14.8:1.14":{"pli":"cetanā …pe… ","html":"{}"},"kv14.8:1.15":{"pli":"cittaṃ abyākatanti? ","html":"{}"},"kv14.8:1.16":{"pli":"Na hevaṃ vattabbe …pe…. ","html":"{}</p>"},"kv14.8:2.1":{"pli":"Diṭṭhigatasampayutto phasso akusaloti? ","html":"<p data-doxy='orthodox'>{}"},"kv14.8:2.2":{"pli":"Āmantā. ","html":"{}"},"kv14.8:2.3":{"pli":"Diṭṭhigataṃ akusalanti? ","html":"{}"},"kv14.8:2.4":{"pli":"Na hevaṃ vattabbe …pe… ","html":"{}"},"kv14.8:2.5":{"pli":"diṭṭhigatasampayuttā vedanā saññā cetanā cittaṃ akusalanti? ","html":"{}"},"kv14.8:2.6":{"pli":"Āmantā. ","html":"{}"},"kv14.8:2.7":{"pli":"Diṭṭhigataṃ akusalanti? ","html":"{}"},"kv14.8:2.8":{"pli":"Na hevaṃ vattabbe …pe…. ","html":"{}</p>"},"kv14.8:3.1":{"pli":"Diṭṭhigataṃ abyākatanti? ","html":"<p data-doxy='orthodox'>{}"},"kv14.8:3.2":{"pli":"Āmantā. ","html":"{}"},"kv14.8:3.3":{"pli":"Aphalaṃ avipākanti? ","html":"{}"},"kv14.8:3.4":{"pli":"Na hevaṃ vattabbe …pe… ","html":"{}"},"kv14.8:3.5":{"pli":"nanu saphalaṃ savipākanti? ","html":"{}"},"kv14.8:3.6":{"pli":"Āmantā. ","html":"{}"},"kv14.8:3.7":{"pli":"Hañci saphalaṃ savipākaṃ, no ca vata re vattabbe—","html":"{}"},"kv14.8:3.8":{"pli":"“diṭṭhigataṃ abyākatan”ti. ","html":"{}</p>"},"kv14.8:4.1":{"pli":"Diṭṭhigataṃ abyākatanti? ","html":"<p data-doxy='orthodox'>{}"},"kv14.8:4.2":{"pli":"Āmantā. ","html":"{}"},"kv14.8:4.3":{"pli":"Nanu micchādiṭṭhiparamāni vajjāni vuttāni bhagavatāti? ","html":"{}"},"kv14.8:4.4":{"pli":"Āmantā. ","html":"{}"},"kv14.8:4.5":{"pli":"Hañci micchādiṭṭhiparamāni vajjāni vuttāni bhagavatā, no ca vata re vattabbe—","html":"{}"},"kv14.8:4.6":{"pli":"“diṭṭhigataṃ abyākatan”ti. ","html":"{}</p>"},"kv14.8:5.1":{"pli":"Diṭṭhigataṃ abyākatanti? ","html":"<p data-doxy='orthodox'>{}"},"kv14.8:5.2":{"pli":"Āmantā. ","html":"{}"},"kv14.8:5.3":{"pli":"Nanu vuttaṃ bhagavatā—","html":"{}"},"kv14.8:5.4":{"pli":"“micchādiṭṭhi kho, vaccha, akusalā, sammādiṭṭhi kusalā”ti. ","html":"{}"},"kv14.8:5.5":{"pli":"Attheva suttantoti? ","html":"{}"},"kv14.8:5.6":{"pli":"Āmantā. ","html":"{}"},"kv14.8:5.7":{"pli":"Tena hi na vattabbaṃ—","html":"{}"},"kv14.8:5.8":{"pli":"“diṭṭhigataṃ abyākatan”ti. ","html":"{}</p>"},"kv14.8:6.1":{"pli":"Diṭṭhigataṃ abyākatanti? ","html":"<p data-doxy='orthodox'>{}"},"kv14.8:6.2":{"pli":"Āmantā. ","html":"{}"},"kv14.8:6.3":{"pli":"Nanu vuttaṃ bhagavatā—","html":"{}"},"kv14.8:6.4":{"pli":"“micchādiṭṭhissa kho ahaṃ, puṇṇa, dvinnaṃ gatīnaṃ aññataraṃ gatiṃ vadāmi—","html":"{}"},"kv14.8:6.5":{"pli":"nirayaṃ vā tiracchānayoniṃ vā”ti. ","html":"{}"},"kv14.8:6.6":{"pli":"Attheva suttantoti? ","html":"{}"},"kv14.8:6.7":{"pli":"Āmantā. ","html":"{}"},"kv14.8:6.8":{"pli":"Tena hi na vattabbaṃ—","html":"{}"},"kv14.8:6.9":{"pli":"“diṭṭhigataṃ abyākatan”ti. ","html":"{}</p>"},"kv14.8:7.1":{"pli":"Na vattabbaṃ—","html":"<p data-doxy='heterodox'>{}"},"kv14.8:7.2":{"pli":"“diṭṭhigataṃ abyākatan”ti? ","html":"{}"},"kv14.8:7.3":{"pli":"Āmantā. ","html":"{}"},"kv14.8:7.4":{"pli":"Nanu vuttaṃ bhagavatā—","html":"{}"},"kv14.8:7.5":{"pli":"“‘sassato loko’ti kho, vaccha, abyākatametaṃ, ","html":"{}"},"kv14.8:7.6":{"pli":"‘asassato loko’ti kho, vaccha, abyākatametaṃ, ","html":"{}"},"kv14.8:7.7":{"pli":"‘antavā loko’ti kho, vaccha, abyākatametaṃ, ","html":"{}"},"kv14.8:7.8":{"pli":"‘anantavā loko’ti kho, vaccha …pe… ","html":"{}"},"kv14.8:7.9":{"pli":"‘taṃ jīvaṃ taṃ sarīran’ti kho, vaccha …pe… ","html":"{}"},"kv14.8:7.10":{"pli":"‘aññaṃ jīvaṃ aññaṃ sarīran’ti kho, vaccha …pe… ","html":"{}"},"kv14.8:7.11":{"pli":"‘hoti tathāgato paraṃ maraṇā’ti kho, vaccha …pe… ","html":"{}"},"kv14.8:7.12":{"pli":"‘na hoti tathāgato paraṃ maraṇā’ti kho, vaccha …pe… ","html":"{}"},"kv14.8:7.13":{"pli":"‘hoti ca na ca hoti tathāgato paraṃ maraṇā’ti kho, vaccha …pe… ","html":"{}"},"kv14.8:7.14":{"pli":"‘neva hoti na na hoti tathāgato paraṃ maraṇā’ti kho, vaccha, abyākatametan”ti. ","html":"{}"},"kv14.8:7.15":{"pli":"Attheva suttantoti? ","html":"{}"},"kv14.8:7.16":{"pli":"Āmantā. ","html":"{}"},"kv14.8:7.17":{"pli":"Tena hi diṭṭhigataṃ abyākatanti. ","html":"{}</p>"},"kv14.8:8.1":{"pli":"Diṭṭhigataṃ abyākatanti? ","html":"<p data-doxy='orthodox'>{}"},"kv14.8:8.2":{"pli":"Āmantā. ","html":"{}"},"kv14.8:8.3":{"pli":"Nanu vuttaṃ bhagavatā—","html":"{}"},"kv14.8:8.4":{"pli":"“micchādiṭṭhikassa, bhikkhave, purisapuggalassa yañceva kāyakammaṃ yathādiṭṭhisamattaṃ samādinnaṃ, yañca vacīkammaṃ …pe… yañca manokammaṃ, yā ca cetanā, yā ca patthanā, yo ca paṇidhi, ye ca saṅkhārā, sabbe te dhammā aniṭṭhāya akantāya amanāpāya ahitāya dukkhāya saṃvattantī”ti. ","html":"{}"},"kv14.8:8.5":{"pli":"Attheva suttantoti? ","html":"{}"},"kv14.8:8.6":{"pli":"Āmantā. ","html":"{}"},"kv14.8:8.7":{"pli":"Tena hi na vattabbaṃ—","html":"{}"},"kv14.8:8.8":{"pli":"“diṭṭhigataṃ abyākatan”ti. ","html":"{}</p>"},"kv14.8:8.9":{"pli":"Abyākatakathā niṭṭhitā. ","html":"<p class='endsutta'>{}</p></article>"}},"kv14.9":{"kv14.9:0.1":{"pli":"Kathāvatthu ","html":"<article id='kv14.9'><header><ul><li class='division'>{}</li>"},"kv14.9:0.2":{"pli":"Mahāpaṇṇāsaka ","html":"<li>{}</li>"},"kv14.9:0.3":{"pli":"Cuddasamavagga ","html":"<li>{}</li></ul>"},"kv14.9:0.4":{"pli":"Apariyāpannakathā ","html":"<h1 class='sutta-title'>{}</h1></header>"},"kv14.9:1.1":{"pli":"Diṭṭhigataṃ apariyāpannanti? ","html":"<p data-doxy='orthodox'>{}"},"kv14.9:1.2":{"pli":"Āmantā. ","html":"{}"},"kv14.9:1.3":{"pli":"Maggo phalaṃ nibbānaṃ, sotāpattimaggo sotāpattiphalaṃ, sakadāgāmimaggo sakadāgāmiphalaṃ, anāgāmimaggo anāgāmiphalaṃ, arahattamaggo arahattaphalaṃ, satipaṭṭhānaṃ sammappadhānaṃ iddhipādo indriyaṃ balaṃ bojjhaṅgoti? ","html":"{}"},"kv14.9:1.4":{"pli":"Na hevaṃ vattabbe …pe…. ","html":"{}</p>"},"kv14.9:2.1":{"pli":"Na vattabbaṃ—","html":"<p data-doxy='heterodox'>{}"},"kv14.9:2.2":{"pli":"“diṭṭhigataṃ apariyāpannan”ti? ","html":"{}"},"kv14.9:2.3":{"pli":"Āmantā. ","html":"{}"},"kv14.9:2.4":{"pli":"Puthujjano “kāmesu vītarāgo”ti vattabboti? ","html":"{}"},"kv14.9:2.5":{"pli":"Āmantā. ","html":"{}"},"kv14.9:2.6":{"pli":"“Vigatadiṭṭhiyo”ti vattabboti? ","html":"{}"},"kv14.9:2.7":{"pli":"Na hevaṃ vattabbe. ","html":"{}"},"kv14.9:2.8":{"pli":"Tena hi diṭṭhigataṃ apariyāpannanti. ","html":"{}</p>"},"kv14.9:2.9":{"pli":"Apariyāpannakathā niṭṭhitā. ","html":"<p class='endsutta'>{}<br>"},"kv14.9:2.10":{"pli":"Cuddasamo vaggo. ","html":"{}</p>"},"kv14.9:2.11":{"pli":"Tassuddānaṃ ","html":"<p class='uddana-intro'>{}</p>"},"kv14.9:3.1":{"pli":"Akusalamūlaṃ paṭisandahati kusalamūlaṃ, ","html":"<p class='uddana'>{}"},"kv14.9:3.2":{"pli":"kusalamūlaṃ paṭisandahati akusalamūlaṃ, ","html":"{}"},"kv14.9:3.3":{"pli":"saḷāyatanaṃ chaviññāṇakāyā, ","html":"{}"},"kv14.9:3.4":{"pli":"ariyarūpaṃ mahābhūtānaṃ upādāya, ","html":"{}"},"kv14.9:3.5":{"pli":"sveva anusayo taṃ pariyuṭṭhānaṃ, ","html":"{}"},"kv14.9:3.6":{"pli":"pariyuṭṭhānaṃ cittavippayuttaṃ, ","html":"{}"},"kv14.9:3.7":{"pli":"yathādhātu taññeva anuseti, ","html":"{}"},"kv14.9:3.8":{"pli":"diṭṭhigataṃ abyākataṃ, ","html":"{}"},"kv14.9:3.9":{"pli":"diṭṭhigataṃ apariyāpannanti. ","html":"{}</p></article>"}},"kv15.1":{"kv15.1:0.1":{"pli":"Kathāvatthu ","html":"<article id='kv15.1'><header><ul><li class='division'>{}</li>"},"kv15.1:0.2":{"pli":"Anusayapaṇṇāsaka ","html":"<li>{}</li>"},"kv15.1:0.3":{"pli":"Pannarasamavagga ","html":"<li>{}</li></ul>"},"kv15.1:0.4":{"pli":"Paccayatākathā ","html":"<h1 class='sutta-title'>{}</h1></header>"},"kv15.1:1.1":{"pli":"Paccayatā vavatthitāti? ","html":"<p data-doxy='orthodox'>{}"},"kv15.1:1.2":{"pli":"Āmantā. ","html":"{}"},"kv15.1:1.3":{"pli":"Nanu vīmaṃsā hetu, so ca adhipatīti? ","html":"{}"},"kv15.1:1.4":{"pli":"Āmantā. ","html":"{}"},"kv15.1:1.5":{"pli":"Hañci vīmaṃsā hetu, so ca adhipati, tena vata re vattabbe—","html":"{}"},"kv15.1:1.6":{"pli":"“hetupaccayena paccayo, adhipatipaccayena paccayo”ti. ","html":"{}</p>"},"kv15.1:2.1":{"pli":"Nanu chandādhipati sahajātānaṃ dhammānaṃ adhipatīti? ","html":"<p data-doxy='orthodox'>{}"},"kv15.1:2.2":{"pli":"Āmantā. ","html":"{}"},"kv15.1:2.3":{"pli":"Hañci chandādhipati sahajātānaṃ dhammānaṃ adhipati, tena vata re vattabbe—","html":"{}"},"kv15.1:2.4":{"pli":"“adhipatipaccayena paccayo, sahajātapaccayena paccayo”ti. ","html":"{}</p>"},"kv15.1:3.1":{"pli":"Nanu vīriyādhipati sahajātānaṃ dhammānaṃ adhipatīti? ","html":"<p data-doxy='orthodox'>{}"},"kv15.1:3.2":{"pli":"Āmantā. ","html":"{}"},"kv15.1:3.3":{"pli":"Hañci vīriyādhipati sahajātānaṃ dhammānaṃ adhipati, tena vata re vattabbe—","html":"{}"},"kv15.1:3.4":{"pli":"“adhipatipaccayena paccayo, sahajātapaccayena paccayo”ti. ","html":"{}</p>"},"kv15.1:4.1":{"pli":"Nanu vīriyādhipati sahajātānaṃ dhammānaṃ adhipati, tañca indriyanti? ","html":"<p data-doxy='orthodox'>{}"},"kv15.1:4.2":{"pli":"Āmantā. ","html":"{}"},"kv15.1:4.3":{"pli":"Hañci vīriyādhipati sahajātānaṃ dhammānaṃ adhipati, tañca indriyaṃ, tena vata re vattabbe—","html":"{}"},"kv15.1:4.4":{"pli":"“adhipatipaccayena paccayo, indriyapaccayena paccayo”ti. ","html":"{}</p>"},"kv15.1:5.1":{"pli":"Nanu vīriyādhipati sahajātānaṃ dhammānaṃ adhipati, tañca maggaṅganti? ","html":"<p data-doxy='orthodox'>{}"},"kv15.1:5.2":{"pli":"Āmantā. ","html":"{}"},"kv15.1:5.3":{"pli":"Hañci vīriyādhipati sahajātānaṃ dhammānaṃ adhipati, tañca maggaṅgaṃ, tena vata re vattabbe—","html":"{}"},"kv15.1:5.4":{"pli":"“adhipatipaccayena paccayo, maggapaccayena paccayo”ti. ","html":"{}</p>"},"kv15.1:6.1":{"pli":"Nanu cittādhipati sahajātānaṃ dhammānaṃ adhipatīti? ","html":"<p data-doxy='orthodox'>{}"},"kv15.1:6.2":{"pli":"Āmantā. ","html":"{}"},"kv15.1:6.3":{"pli":"Hañci cittādhipati sahajātānaṃ dhammānaṃ adhipati, tena vata re vattabbe—","html":"{}"},"kv15.1:6.4":{"pli":"“adhipatipaccayena paccayo, sahajātapaccayena paccayo”ti. ","html":"{}</p>"},"kv15.1:7.1":{"pli":"Nanu cittādhipati sahajātānaṃ dhammānaṃ adhipati, so ca āhāroti? ","html":"<p data-doxy='orthodox'>{}"},"kv15.1:7.2":{"pli":"Āmantā. ","html":"{}"},"kv15.1:7.3":{"pli":"Hañci cittādhipati sahajātānaṃ dhammānaṃ adhipati, so ca āhāro, tena vata re vattabbe—","html":"{}"},"kv15.1:7.4":{"pli":"“adhipatipaccayena paccayo, āhārapaccayena paccayo”ti. ","html":"{}</p>"},"kv15.1:8.1":{"pli":"Nanu cittādhipati sahajātānaṃ dhammānaṃ adhipati, tañca indriyanti? ","html":"<p data-doxy='orthodox'>{}"},"kv15.1:8.2":{"pli":"Āmantā. ","html":"{}"},"kv15.1:8.3":{"pli":"Hañci cittādhipati sahajātānaṃ dhammānaṃ adhipati, tañca indriyaṃ, tena vata re vattabbe—","html":"{}"},"kv15.1:8.4":{"pli":"“adhipatipaccayena paccayo, indriyapaccayena paccayo”ti. ","html":"{}</p>"},"kv15.1:9.1":{"pli":"Nanu vīmaṃsādhipati sahajātānaṃ dhammānaṃ adhipatīti? ","html":"<p data-doxy='orthodox'>{}"},"kv15.1:9.2":{"pli":"Āmantā. ","html":"{}"},"kv15.1:9.3":{"pli":"Hañci vīmaṃsādhipati sahajātānaṃ dhammānaṃ adhipati, tena vata re vattabbe—","html":"{}"},"kv15.1:9.4":{"pli":"“adhipatipaccayena paccayo, sahajātapaccayena paccayo”ti. ","html":"{}</p>"},"kv15.1:10.1":{"pli":"Nanu vīmaṃsādhipati sahajātānaṃ dhammānaṃ adhipati, tañca indriyanti? ","html":"<p data-doxy='orthodox'>{}"},"kv15.1:10.2":{"pli":"Āmantā. ","html":"{}"},"kv15.1:10.3":{"pli":"Hañci vīmaṃsādhipati sahajātānaṃ dhammānaṃ adhipati, tañca indriyaṃ, tena vata re vattabbe—","html":"{}"},"kv15.1:10.4":{"pli":"“adhipatipaccayena paccayo, indriyapaccayena paccayo”ti. ","html":"{}</p>"},"kv15.1:11.1":{"pli":"Nanu vīmaṃsādhipati sahajātānaṃ dhammānaṃ adhipati, tañca maggaṅganti? ","html":"<p data-doxy='orthodox'>{}"},"kv15.1:11.2":{"pli":"Āmantā. ","html":"{}"},"kv15.1:11.3":{"pli":"Hañci vīmaṃsādhipati sahajātānaṃ dhammānaṃ adhipati, tañca maggaṅgaṃ, tena vata re vattabbe—","html":"{}"},"kv15.1:11.4":{"pli":"“adhipatipaccayena paccayo, maggapaccayena paccayo”ti. ","html":"{}</p>"},"kv15.1:12.1":{"pli":"Nanu ariyaṃ dhammaṃ garuṃ katvā uppajjati paccavekkhaṇā, tañcārammaṇanti? ","html":"<p data-doxy='orthodox'>{}"},"kv15.1:12.2":{"pli":"Āmantā. ","html":"{}"},"kv15.1:12.3":{"pli":"Hañci ariyaṃ dhammaṃ garuṃ katvā uppajjati paccavekkhaṇā, tañcārammaṇaṃ, tena vata re vattabbe—","html":"{}"},"kv15.1:12.4":{"pli":"“adhipatipaccayena paccayo, ārammaṇapaccayena paccayo”ti. ","html":"{}</p>"},"kv15.1:13.1":{"pli":"Nanu purimā purimā kusalā dhammā pacchimānaṃ pacchimānaṃ kusalānaṃ dhammānaṃ anantarapaccayena paccayo, sā ca āsevanāti? ","html":"<p data-doxy='orthodox'>{}"},"kv15.1:13.2":{"pli":"Āmantā. ","html":"{}"},"kv15.1:13.3":{"pli":"Hañci purimā purimā kusalā dhammā pacchimānaṃ pacchimānaṃ kusalānaṃ dhammānaṃ anantarapaccayena paccayo, sā ca āsevanā, tena vata re vattabbe—","html":"{}"},"kv15.1:13.4":{"pli":"“anantarapaccayena paccayo, āsevanapaccayena paccayo”ti. ","html":"{}</p>"},"kv15.1:14.1":{"pli":"Nanu purimā purimā akusalā dhammā pacchimānaṃ pacchimānaṃ akusalānaṃ dhammānaṃ anantarapaccayena paccayo, sā ca āsevanāti? ","html":"<p data-doxy='orthodox'>{}"},"kv15.1:14.2":{"pli":"Āmantā. ","html":"{}"},"kv15.1:14.3":{"pli":"Hañci purimā purimā akusalā dhammā pacchimānaṃ pacchimānaṃ akusalānaṃ dhammānaṃ anantarapaccayena paccayo, sā ca āsevanā, tena vata re vattabbe—","html":"{}"},"kv15.1:14.4":{"pli":"“anantarapaccayena paccayo, āsevanapaccayena paccayo”ti. ","html":"{}</p>"},"kv15.1:15.1":{"pli":"Nanu purimā purimā kiriyābyākatā dhammā pacchimānaṃ pacchimānaṃ kiriyābyākatānaṃ dhammānaṃ anantarapaccayena paccayo, sā ca āsevanāti? ","html":"<p data-doxy='orthodox'>{}"},"kv15.1:15.2":{"pli":"Āmantā. ","html":"{}"},"kv15.1:15.3":{"pli":"Hañci purimā purimā kiriyābyākatā dhammā pacchimānaṃ pacchimānaṃ kiriyābyākatānaṃ dhammānaṃ anantarapaccayena paccayo, sā ca āsevanā, tena vata re vattabbe—","html":"{}"},"kv15.1:15.4":{"pli":"“anantarapaccayena paccayo, āsevanapaccayena paccayo”ti. ","html":"{}</p>"},"kv15.1:16.1":{"pli":"Na vattabbaṃ—","html":"<p data-doxy='orthodox'>{}"},"kv15.1:16.2":{"pli":"“paccayatā vavatthitā”ti? ","html":"{}"},"kv15.1:16.3":{"pli":"Āmantā. ","html":"{}"},"kv15.1:16.4":{"pli":"Hetupaccayena paccayo hoti, ārammaṇapaccayena paccayo hoti, anantarapaccayena paccayo hoti, samanantarapaccayena paccayo hotīti? ","html":"{}"},"kv15.1:16.5":{"pli":"Na hevaṃ vattabbe. ","html":"{}"},"kv15.1:16.6":{"pli":"Tena hi paccayatā vavatthitāti. ","html":"{}</p>"},"kv15.1:16.7":{"pli":"Paccayatākathā niṭṭhitā. ","html":"<p class='endsutta'>{}</p></article>"}}}