{"kv7.5":{"kv7.5:0.1":{"pli":"Kathāvatthu ","html":"<article id='kv7.5'><header><ul><li class='division'>{}</li>"},"kv7.5:0.2":{"pli":"Mahāpaṇṇāsaka ","html":"<li>{}</li>"},"kv7.5:0.3":{"pli":"Sattamavagga ","html":"<li>{}</li></ul>"},"kv7.5:0.4":{"pli":"Paribhogamayapuññakathā ","html":"<h1 class='sutta-title'>{}</h1></header>"},"kv7.5:1.1":{"pli":"Paribhogamayaṃ puññaṃ vaḍḍhatīti? ","html":"<p data-doxy='orthodox'>{}"},"kv7.5:1.2":{"pli":"Āmantā. ","html":"{}"},"kv7.5:1.3":{"pli":"Paribhogamayo phasso vaḍḍhati, vedanā vaḍḍhati, saññā vaḍḍhati, cetanā vaḍḍhati, cittaṃ vaḍḍhati, saddhā vaḍḍhati, vīriyaṃ vaḍḍhati, sati vaḍḍhati, samādhi vaḍḍhati, paññā vaḍḍhatīti? ","html":"{}"},"kv7.5:1.4":{"pli":"Na hevaṃ vattabbe …pe…. ","html":"{}</p>"},"kv7.5:2.1":{"pli":"Paribhogamayaṃ puññaṃ vaḍḍhatīti? ","html":"<p data-doxy='orthodox'>{}"},"kv7.5:2.2":{"pli":"Āmantā. ","html":"{}"},"kv7.5:2.3":{"pli":"Latā viya vaḍḍhati, māluvā viya vaḍḍhati, rukkho viya vaḍḍhati, tiṇaṃ viya vaḍḍhati, muñjapuñjo viya vaḍḍhatīti? ","html":"{}"},"kv7.5:2.4":{"pli":"Na hevaṃ vattabbe …pe…. ","html":"{}</p>"},"kv7.5:3.1":{"pli":"Paribhogamayaṃ puññaṃ vaḍḍhatīti? ","html":"<p data-doxy='orthodox'>{}"},"kv7.5:3.2":{"pli":"Āmantā. ","html":"{}"},"kv7.5:3.3":{"pli":"Dāyako dānaṃ datvā na samannāharati, hoti puññanti? ","html":"{}"},"kv7.5:3.4":{"pli":"Āmantā. ","html":"{}"},"kv7.5:3.5":{"pli":"Anāvaṭṭentassa hoti … ","html":"{}"},"kv7.5:3.6":{"pli":"anābhogassa hoti … ","html":"{}"},"kv7.5:3.7":{"pli":"asamannāharantassa hoti … ","html":"{}"},"kv7.5:3.8":{"pli":"amanasikarontassa hoti … ","html":"{}"},"kv7.5:3.9":{"pli":"acetayantassa hoti … ","html":"{}"},"kv7.5:3.10":{"pli":"apatthayantassa hoti … appaṇidahantassa hotīti? ","html":"{}"},"kv7.5:3.11":{"pli":"Na hevaṃ vattabbe …pe… ","html":"{}"},"kv7.5:3.12":{"pli":"nanu āvaṭṭentassa hoti … ","html":"{}"},"kv7.5:3.13":{"pli":"ābhogassa hoti … ","html":"{}"},"kv7.5:3.14":{"pli":"samannāharantassa hoti … ","html":"{}"},"kv7.5:3.15":{"pli":"manasikarontassa hoti … ","html":"{}"},"kv7.5:3.16":{"pli":"cetayantassa hoti … ","html":"{}"},"kv7.5:3.17":{"pli":"patthayantassa hoti … paṇidahantassa hotīti? ","html":"{}"},"kv7.5:3.18":{"pli":"Āmantā. ","html":"{}"},"kv7.5:3.19":{"pli":"Hañci āvaṭṭentassa hoti … ","html":"{}"},"kv7.5:3.20":{"pli":"ābhogassa hoti … ","html":"{}"},"kv7.5:3.21":{"pli":"samannāharantassa hoti … ","html":"{}"},"kv7.5:3.22":{"pli":"manasikarontassa hoti … ","html":"{}"},"kv7.5:3.23":{"pli":"cetayantassa hoti … ","html":"{}"},"kv7.5:3.24":{"pli":"patthayantassa hoti … paṇidahantassa hoti, no ca vata re vattabbe—","html":"{}"},"kv7.5:3.25":{"pli":"“paribhogamayaṃ puññaṃ vaḍḍhatī”ti. ","html":"{}</p>"},"kv7.5:4.1":{"pli":"Paribhogamayaṃ puññaṃ vaḍḍhatīti? ","html":"<p data-doxy='orthodox'>{}"},"kv7.5:4.2":{"pli":"Āmantā. ","html":"{}"},"kv7.5:4.3":{"pli":"Dāyako dānaṃ datvā kāmavitakkaṃ vitakketi, byāpādavitakkaṃ vitakketi, vihiṃsāvitakkaṃ vitakketi, hoti puññanti? ","html":"{}"},"kv7.5:4.4":{"pli":"Āmantā. ","html":"{}"},"kv7.5:4.5":{"pli":"Dvinnaṃ phassānaṃ …pe… ","html":"{}"},"kv7.5:4.6":{"pli":"dvinnaṃ cittānaṃ samodhānaṃ hotīti? ","html":"{}"},"kv7.5:4.7":{"pli":"Na hevaṃ vattabbe …pe… ","html":"{}"},"kv7.5:4.8":{"pli":"dvinnaṃ phassānaṃ …pe… ","html":"{}"},"kv7.5:4.9":{"pli":"dvinnaṃ cittānaṃ samodhānaṃ hotīti? ","html":"{}"},"kv7.5:4.10":{"pli":"Āmantā. ","html":"{}"},"kv7.5:4.11":{"pli":"Kusalākusalā sāvajjānavajjā hīnapaṇītā kaṇhasukkasappaṭibhāgā dhammā sammukhībhāvaṃ āgacchantīti? ","html":"{}"},"kv7.5:4.12":{"pli":"Na hevaṃ vattabbe …pe… ","html":"{}"},"kv7.5:4.13":{"pli":"kusalākusalā sāvajjānavajjā hīnapaṇītā kaṇhasukkasappaṭibhāgā dhammā sammukhībhāvaṃ āgacchantīti? ","html":"{}"},"kv7.5:4.14":{"pli":"Āmantā. ","html":"{}"},"kv7.5:4.15":{"pli":"Nanu vuttaṃ bhagavatā—","html":"{}"},"kv7.5:4.16":{"pli":"“cattārimāni, bhikkhave, suvidūravidūrāni. ","html":"{}"},"kv7.5:4.17":{"pli":"Katamāni cattāri? ","html":"{}"},"kv7.5:4.18":{"pli":"Nabhañca, bhikkhave, pathavī ca—","html":"{}"},"kv7.5:4.19":{"pli":"idaṃ paṭhamaṃ suvidūravidūraṃ. ","html":"{}"},"kv7.5:4.20":{"pli":"Orimañca, bhikkhave, tīraṃ samuddassa pārimañca tīraṃ—","html":"{}"},"kv7.5:4.21":{"pli":"idaṃ dutiyaṃ suvidūravidūraṃ. ","html":"{}"},"kv7.5:4.22":{"pli":"Yato ca, bhikkhave, verocano abbhudeti yattha ca atthameti—","html":"{}"},"kv7.5:4.23":{"pli":"idaṃ tatiyaṃ suvidūravidūraṃ. ","html":"{}"},"kv7.5:4.24":{"pli":"Satañca, bhikkhave, dhammo asatañca dhammo—","html":"{}"},"kv7.5:4.25":{"pli":"idaṃ catutthaṃ suvidūravidūraṃ. ","html":"{}"},"kv7.5:4.26":{"pli":"Imāni kho, bhikkhave, cattāri suvidūravidūrānīti. ","html":"{}</p>"},"kv7.5:5.1":{"pli":"Nabhañca dūre pathavī ca dūre, ","html":"<blockquote class='gatha'><p><span class='verse-line'>{}</span>"},"kv7.5:5.2":{"pli":"Pāraṃ samuddassa tadāhu dūre; ","html":"<span class='verse-line'>{}</span>"},"kv7.5:5.3":{"pli":"Yato ca verocano abbhudeti, ","html":"<span class='verse-line'>{}</span>"},"kv7.5:5.4":{"pli":"Pabhaṅkaro yattha ca atthameti; ","html":"<span class='verse-line'>{}</span>"},"kv7.5:5.5":{"pli":"Tato have dūrataraṃ vadanti, ","html":"<span class='verse-line'>{}</span>"},"kv7.5:5.6":{"pli":"Satañca dhammaṃ asatañca dhammaṃ. ","html":"<span class='verse-line'>{}</span></p>"},"kv7.5:6.1":{"pli":"Abyāyiko hoti sataṃ samāgamo, ","html":"<p><span class='verse-line'>{}</span>"},"kv7.5:6.2":{"pli":"Yāvampi tiṭṭheyya tatheva hoti; ","html":"<span class='verse-line'>{}</span>"},"kv7.5:6.3":{"pli":"Khippañhi veti asataṃ samāgamo, ","html":"<span class='verse-line'>{}</span>"},"kv7.5:6.4":{"pli":"Tasmā sataṃ dhammo asabbhi ārakā”ti. ","html":"<span class='verse-line'>{}</span></p></blockquote>"},"kv7.5:7.1":{"pli":"Attheva suttantoti? ","html":"<p>{}"},"kv7.5:7.2":{"pli":"Āmantā. ","html":"{}"},"kv7.5:7.3":{"pli":"Tena hi na vattabbaṃ—","html":"{}"},"kv7.5:7.4":{"pli":"“kusalākusalā sāvajjānavajjā hīnapaṇītā kaṇhasukkasappaṭibhāgā dhammā sammukhībhāvaṃ āgacchantī”ti. ","html":"{}</p>"},"kv7.5:8.1":{"pli":"Na vattabbaṃ—","html":"<p data-doxy='heterodox'>{}"},"kv7.5:8.2":{"pli":"“paribhogamayaṃ puññaṃ vaḍḍhatī”ti? ","html":"{}"},"kv7.5:8.3":{"pli":"Āmantā. ","html":"{}"},"kv7.5:8.4":{"pli":"Nanu vuttaṃ bhagavatā—","html":"{}</p>"},"kv7.5:9.1":{"pli":"“Ārāmaropā vanaropā, ","html":"<blockquote class='gatha'><p><span class='verse-line'>{}</span>"},"kv7.5:9.2":{"pli":"ye janā setukārakā; ","html":"<span class='verse-line'>{}</span>"},"kv7.5:9.3":{"pli":"Papañca udapānañca, ","html":"<span class='verse-line'>{}</span>"},"kv7.5:9.4":{"pli":"ye dadanti upassayaṃ. ","html":"<span class='verse-line'>{}</span></p>"},"kv7.5:10.1":{"pli":"Tesaṃ divā ca ratto ca, ","html":"<p><span class='verse-line'>{}</span>"},"kv7.5:10.2":{"pli":"sadā puññaṃ pavaḍḍhati; ","html":"<span class='verse-line'>{}</span>"},"kv7.5:10.3":{"pli":"Dhammaṭṭhā sīlasampannā, ","html":"<span class='verse-line'>{}</span>"},"kv7.5:10.4":{"pli":"te janā saggagāmino”ti. ","html":"<span class='verse-line'>{}</span></p></blockquote>"},"kv7.5:11.1":{"pli":"Attheva suttantoti? ","html":"<p>{}"},"kv7.5:11.2":{"pli":"Āmantā. ","html":"{}"},"kv7.5:11.3":{"pli":"Tena hi paribhogamayaṃ puññaṃ vaḍḍhatīti. ","html":"{}</p>"},"kv7.5:12.1":{"pli":"Na vattabbaṃ—","html":"<p data-doxy='heterodox'>{}"},"kv7.5:12.2":{"pli":"“paribhogamayaṃ puññaṃ vaḍḍhatī”ti? ","html":"{}"},"kv7.5:12.3":{"pli":"Āmantā. ","html":"{}"},"kv7.5:12.4":{"pli":"Nanu vuttaṃ bhagavatā—","html":"{}"},"kv7.5:12.5":{"pli":"“cattārome, bhikkhave, puññābhisandā kusalābhisandā sukhassāhārā sovaggikā sukhavipākā saggasaṃvattanikā iṭṭhāya kantāya manāpāya hitāya sukhāya saṃvattanti. ","html":"{}"},"kv7.5:12.6":{"pli":"Katame cattāro? ","html":"{}"},"kv7.5:12.7":{"pli":"Yassa, bhikkhave, bhikkhu cīvaraṃ paribhuñjamāno appamāṇaṃ cetosamādhiṃ upasampajja viharati, appamāṇo tassa puññābhisando kusalābhisando sukhassāhāro sovaggiko sukhavipāko saggasaṃvattaniko iṭṭhāya kantāya manāpāya hitāya sukhāya saṃvattati. ","html":"{}"},"kv7.5:12.8":{"pli":"Yassa, bhikkhave, bhikkhu piṇḍapātaṃ paribhuñjamāno …pe… ","html":"{}"},"kv7.5:12.9":{"pli":"senāsanaṃ paribhuñjamāno …pe… ","html":"{}"},"kv7.5:12.10":{"pli":"gilānapaccayabhesajjaparikkhāraṃ paribhuñjamāno appamāṇaṃ cetosamādhiṃ upasampajja viharati, appamāṇo tassa puññābhisando kusalābhisando sukhassāhāro sovaggiko sukhavipāko saggasaṃvattaniko iṭṭhāya kantāya manāpāya hitāya sukhāya saṃvattati. ","html":"{}"},"kv7.5:12.11":{"pli":"Ime kho, bhikkhave, cattāro puññābhisandā kusalābhisandā sukhassāhārā sovaggikā sukhavipākā saggasaṃvattanikā iṭṭhāya kantāya manāpāya hitāya sukhāya saṃvattantī”ti. ","html":"{}"},"kv7.5:12.12":{"pli":"Attheva suttantoti? ","html":"{}"},"kv7.5:12.13":{"pli":"Āmantā. ","html":"{}"},"kv7.5:12.14":{"pli":"Tena hi paribhogamayaṃ puññaṃ vaḍḍhatīti. ","html":"{}</p>"},"kv7.5:13.1":{"pli":"Paribhogamayaṃ puññaṃ vaḍḍhatīti? ","html":"<p data-doxy='orthodox'>{}"},"kv7.5:13.2":{"pli":"Āmantā. ","html":"{}"},"kv7.5:13.3":{"pli":"Dāyako dānaṃ deti, paṭiggāhako paṭiggahetvā na paribhuñjati chaḍḍeti vissajjeti, hoti puññanti? ","html":"{}"},"kv7.5:13.4":{"pli":"Āmantā. ","html":"{}"},"kv7.5:13.5":{"pli":"Hañci dāyako dānaṃ deti, paṭiggāhako paṭiggahetvā na paribhuñjati chaḍḍeti vissajjeti, hoti puññaṃ; ","html":"{}"},"kv7.5:13.6":{"pli":"no ca vata re vattabbe—","html":"{}"},"kv7.5:13.7":{"pli":"“paribhogamayaṃ puññaṃ vaḍḍhatī”ti. ","html":"{}</p>"},"kv7.5:14.1":{"pli":"Paribhogamayaṃ puññaṃ vaḍḍhatīti? ","html":"<p data-doxy='orthodox'>{}"},"kv7.5:14.2":{"pli":"Āmantā. ","html":"{}"},"kv7.5:14.3":{"pli":"Dāyako dānaṃ deti, paṭiggāhake paṭiggahite rājāno vā haranti, corā vā haranti, aggi vā dahati, udakaṃ vā vahati, appiyā vā dāyādā haranti, hoti puññanti? ","html":"{}"},"kv7.5:14.4":{"pli":"Āmantā. ","html":"{}"},"kv7.5:14.5":{"pli":"Hañci dāyako dānaṃ deti, paṭiggāhake paṭiggahite rājāno vā haranti, corā vā haranti, aggi vā dahati, udakaṃ vā vahati, appiyā vā dāyādā haranti, hoti puññaṃ; ","html":"{}"},"kv7.5:14.6":{"pli":"no ca vata re vattabbe—","html":"{}"},"kv7.5:14.7":{"pli":"“paribhogamayaṃ puññaṃ vaḍḍhatī”ti. ","html":"{}</p>"},"kv7.5:14.8":{"pli":"Paribhogamayapuññakathā niṭṭhitā. ","html":"<p class='endsutta'>{}</p></article>"}},"kv7.6":{"kv7.6:0.1":{"pli":"Kathāvatthu ","html":"<article id='kv7.6'><header><ul><li class='division'>{}</li>"},"kv7.6:0.2":{"pli":"Mahāpaṇṇāsaka ","html":"<li>{}</li>"},"kv7.6:0.3":{"pli":"Sattamavagga ","html":"<li>{}</li></ul>"},"kv7.6:0.4":{"pli":"Itodinnakathā ","html":"<h1 class='sutta-title'>{}</h1></header>"},"kv7.6:1.1":{"pli":"Ito dinnena tattha yāpentīti? ","html":"<p data-doxy='orthodox'>{}"},"kv7.6:1.2":{"pli":"Āmantā. ","html":"{}"},"kv7.6:1.3":{"pli":"Ito cīvaraṃ denti taṃ cīvaraṃ tattha paribhuñjantīti? ","html":"{}"},"kv7.6:1.4":{"pli":"Na hevaṃ vattabbe …pe… ","html":"{}"},"kv7.6:1.5":{"pli":"ito piṇḍapātaṃ denti, ito senāsanaṃ denti, ito gilānapaccayabhesajjaparikkhāraṃ denti, ito khādanīyaṃ denti, ito bhojanīyaṃ denti, ito pānīyaṃ denti; ","html":"{}"},"kv7.6:1.6":{"pli":"taṃ pānīyaṃ tattha paribhuñjantīti? ","html":"{}"},"kv7.6:1.7":{"pli":"Na hevaṃ vattabbe …pe…. ","html":"{}</p>"},"kv7.6:2.1":{"pli":"Ito dinnena tattha yāpentīti? ","html":"<p data-doxy='orthodox'>{}"},"kv7.6:2.2":{"pli":"Āmantā. ","html":"{}"},"kv7.6:2.3":{"pli":"Añño aññassa kārako parakataṃ sukhadukkhaṃ añño karoti, añño paṭisaṃvedetīti? ","html":"{}"},"kv7.6:2.4":{"pli":"Na hevaṃ vattabbe …pe…. ","html":"{}</p>"},"kv7.6:3.1":{"pli":"Na vattabbaṃ—","html":"<p data-doxy='heterodox'>{}"},"kv7.6:3.2":{"pli":"“ito dinnena tattha yāpentī”ti? ","html":"{}"},"kv7.6:3.3":{"pli":"Āmantā. ","html":"{}"},"kv7.6:3.4":{"pli":"Nanu petā attano atthāya dānaṃ dentaṃ anumodenti, cittaṃ pasādenti, pītiṃ uppādenti, somanassaṃ paṭilabhantīti? ","html":"{}"},"kv7.6:3.5":{"pli":"Āmantā. ","html":"{}"},"kv7.6:3.6":{"pli":"Hañci petā attano atthāya dānaṃ dentaṃ anumodenti, cittaṃ pasādenti, pītiṃ uppādenti, somanassaṃ paṭilabhanti; ","html":"{}"},"kv7.6:3.7":{"pli":"tena vata re vattabbe—","html":"{}"},"kv7.6:3.8":{"pli":"“ito dinnena tattha yāpentī”ti. ","html":"{}</p>"},"kv7.6:4.1":{"pli":"Na vattabbaṃ—","html":"<p data-doxy='heterodox'>{}"},"kv7.6:4.2":{"pli":"“ito dinnena tattha yāpentī”ti? ","html":"{}"},"kv7.6:4.3":{"pli":"Āmantā. ","html":"{}"},"kv7.6:4.4":{"pli":"Nanu vuttaṃ bhagavatā—","html":"{}</p>"},"kv7.6:5.1":{"pli":"“Unname udakaṃ vuṭṭhaṃ, ","html":"<blockquote class='gatha'><p><span class='verse-line'>{}</span>"},"kv7.6:5.2":{"pli":"yathāninnaṃ pavattati; ","html":"<span class='verse-line'>{}</span>"},"kv7.6:5.3":{"pli":"Evameva ito dinnaṃ, ","html":"<span class='verse-line'>{}</span>"},"kv7.6:5.4":{"pli":"petānaṃ upakappati. ","html":"<span class='verse-line'>{}</span></p>"},"kv7.6:6.1":{"pli":"Yathā vārivahā pūrā, ","html":"<p><span class='verse-line'>{}</span>"},"kv7.6:6.2":{"pli":"paripūrenti sāgaraṃ; ","html":"<span class='verse-line'>{}</span>"},"kv7.6:6.3":{"pli":"Evameva ito dinnaṃ, ","html":"<span class='verse-line'>{}</span>"},"kv7.6:6.4":{"pli":"petānaṃ upakappati. ","html":"<span class='verse-line'>{}</span></p>"},"kv7.6:7.1":{"pli":"Na hi tattha kasī atthi, ","html":"<p><span class='verse-line'>{}</span>"},"kv7.6:7.2":{"pli":"gorakkhettha na vijjati; ","html":"<span class='verse-line'>{}</span>"},"kv7.6:7.3":{"pli":"Vaṇijjā tādisī natthi, ","html":"<span class='verse-line'>{}</span>"},"kv7.6:7.4":{"pli":"hiraññena kayākayaṃ; ","html":"<span class='verse-line'>{}</span>"},"kv7.6:7.5":{"pli":"Ito dinnena yāpenti, ","html":"<span class='verse-line'>{}</span>"},"kv7.6:7.6":{"pli":"petā kālaṅkatā tahin”ti. ","html":"<span class='verse-line'>{}</span></p></blockquote>"},"kv7.6:8.1":{"pli":"Attheva suttantoti? ","html":"<p>{}"},"kv7.6:8.2":{"pli":"Āmantā. ","html":"{}"},"kv7.6:8.3":{"pli":"Tena hi ito dinnena tattha yāpentīti. ","html":"{}</p>"},"kv7.6:9.1":{"pli":"Na vattabbaṃ—","html":"<p data-doxy='heterodox'>{}"},"kv7.6:9.2":{"pli":"“ito dinnena tattha yāpentī”ti? ","html":"{}"},"kv7.6:9.3":{"pli":"Āmantā. ","html":"{}"},"kv7.6:9.4":{"pli":"Nanu vuttaṃ bhagavatā—","html":"{}"},"kv7.6:9.5":{"pli":"“pañcimāni, bhikkhave, ṭhānāni sampassantā mātāpitaro puttaṃ icchanti kule jāyamānaṃ. ","html":"{}"},"kv7.6:9.6":{"pli":"Katamāni pañca? ","html":"{}"},"kv7.6:9.7":{"pli":"Bhaṭo vā no bharissati, kiccaṃ vā no karissati, kulavaṃso ciraṃ ṭhassati, dāyajjaṃ paṭipajjissati, atha vā pana petānaṃ kālaṅkatānaṃ dakkhiṇaṃ anuppadassati—","html":"{}"},"kv7.6:9.8":{"pli":"imāni kho, bhikkhave, pañca ṭhānāni sampassantā mātāpitaro puttaṃ icchanti kule jāyamānanti. ","html":"{}</p>"},"kv7.6:10.1":{"pli":"Pañca ṭhānāni sampassaṃ, ","html":"<blockquote class='gatha'><p><span class='verse-line'>{}</span>"},"kv7.6:10.2":{"pli":"puttaṃ icchanti paṇḍitā; ","html":"<span class='verse-line'>{}</span>"},"kv7.6:10.3":{"pli":"Bhaṭo vā no bharissati, ","html":"<span class='verse-line'>{}</span>"},"kv7.6:10.4":{"pli":"kiccaṃ vā no karissati. ","html":"<span class='verse-line'>{}</span></p>"},"kv7.6:11.1":{"pli":"Kulavaṃso ciraṃ tiṭṭhe, ","html":"<p><span class='verse-line'>{}</span>"},"kv7.6:11.2":{"pli":"dāyajjaṃ paṭipajjati; ","html":"<span class='verse-line'>{}</span>"},"kv7.6:11.3":{"pli":"Atha vā pana petānaṃ, ","html":"<span class='verse-line'>{}</span>"},"kv7.6:11.4":{"pli":"dakkhiṇaṃ anuppadassati. ","html":"<span class='verse-line'>{}</span></p>"},"kv7.6:12.1":{"pli":"Ṭhānānetāni sampassaṃ, ","html":"<p><span class='verse-line'>{}</span>"},"kv7.6:12.2":{"pli":"puttaṃ icchanti paṇḍitā; ","html":"<span class='verse-line'>{}</span>"},"kv7.6:12.3":{"pli":"Tasmā santo sappurisā, ","html":"<span class='verse-line'>{}</span>"},"kv7.6:12.4":{"pli":"kataññū katavedino. ","html":"<span class='verse-line'>{}</span></p>"},"kv7.6:13.1":{"pli":"Bharanti mātāpitaro, ","html":"<p><span class='verse-line'>{}</span>"},"kv7.6:13.2":{"pli":"pubbe katamanussaraṃ; ","html":"<span class='verse-line'>{}</span>"},"kv7.6:13.3":{"pli":"Karonti tesaṃ kiccāni, ","html":"<span class='verse-line'>{}</span>"},"kv7.6:13.4":{"pli":"yathā taṃ pubbakārinaṃ. ","html":"<span class='verse-line'>{}</span></p>"},"kv7.6:14.1":{"pli":"Ovādakārī bhaṭaposī, ","html":"<p><span class='verse-line'>{}</span>"},"kv7.6:14.2":{"pli":"kulavaṃsaṃ ahāpayaṃ; ","html":"<span class='verse-line'>{}</span>"},"kv7.6:14.3":{"pli":"Saddho sīlena sampanno, ","html":"<span class='verse-line'>{}</span>"},"kv7.6:14.4":{"pli":"putto hoti pasaṃsiyo”ti. ","html":"<span class='verse-line'>{}</span></p></blockquote>"},"kv7.6:15.1":{"pli":"Attheva suttantoti? ","html":"<p>{}"},"kv7.6:15.2":{"pli":"Āmantā. ","html":"{}"},"kv7.6:15.3":{"pli":"Tena hi ito dinnena tattha yāpentīti. ","html":"{}</p>"},"kv7.6:15.4":{"pli":"Ito dinnakathā niṭṭhitā. ","html":"<p class='endsutta'>{}</p></article>"}},"kv7.7":{"kv7.7:0.1":{"pli":"Kathāvatthu ","html":"<article id='kv7.7'><header><ul><li class='division'>{}</li>"},"kv7.7:0.2":{"pli":"Mahāpaṇṇāsaka ","html":"<li>{}</li>"},"kv7.7:0.3":{"pli":"Sattamavagga ","html":"<li>{}</li></ul>"},"kv7.7:0.4":{"pli":"Pathavīkammavipākotikathā ","html":"<h1 class='sutta-title'>{}</h1></header>"},"kv7.7:1.1":{"pli":"Pathavī kammavipākoti? ","html":"<p data-doxy='orthodox'>{}"},"kv7.7:1.2":{"pli":"Āmantā. ","html":"{}"},"kv7.7:1.3":{"pli":"Sukhavedaniyā dukkhavedaniyā adukkhamasukhavedaniyā, sukhāya vedanāya sampayuttā, dukkhāya vedanāya sampayuttā, adukkhamasukhāya vedanāya sampayuttā, phassena sampayuttā, vedanāya sampayuttā, saññāya sampayuttā, cetanāya sampayuttā, cittena sampayuttā, sārammaṇā; ","html":"{}"},"kv7.7:1.4":{"pli":"atthi tāya āvaṭṭanā ābhogo samannāhāro manasikāro cetanā patthanā paṇidhīti? ","html":"{}"},"kv7.7:1.5":{"pli":"Na hevaṃ vattabbe …pe… ","html":"{}"},"kv7.7:1.6":{"pli":"nanu na sukhavedaniyā na dukkhavedaniyā na adukkhamasukhavedaniyā, na sukhāya vedanāya sampayuttā, na dukkhāya vedanāya sampayuttā, na adukkhamasukhāya vedanāya sampayuttā, na phassena sampayuttā, na vedanāya sampayuttā, na saññāya sampayuttā, na cetanāya sampayuttā, na cittena sampayuttā, anārammaṇā; ","html":"{}"},"kv7.7:1.7":{"pli":"natthi tāya āvaṭṭanā ābhogo samannāhāro manasikāro cetanā patthanā paṇidhīti? ","html":"{}"},"kv7.7:1.8":{"pli":"Āmantā. ","html":"{}"},"kv7.7:1.9":{"pli":"Hañci na sukhavedaniyā na dukkhavedaniyā …pe… ","html":"{}"},"kv7.7:1.10":{"pli":"anārammaṇā; ","html":"{}"},"kv7.7:1.11":{"pli":"natthi tāya āvaṭṭanā …pe… paṇidhi, no ca vata re vattabbe—","html":"{}"},"kv7.7:1.12":{"pli":"“pathavī kammavipāko”ti. ","html":"{}</p>"},"kv7.7:2.1":{"pli":"Phasso kammavipāko, phasso sukhavedaniyo dukkhavedaniyo adukkhamasukhavedaniyo sukhāya vedanāya sampayutto dukkhāya …pe… adukkhamasukhāya vedanāya sampayutto phassena sampayutto vedanāya sampayutto saññāya sampayutto cetanāya sampayutto cittena sampayutto sārammaṇo; ","html":"<p data-doxy='orthodox'>{}"},"kv7.7:2.2":{"pli":"atthi tassa āvaṭṭanā …pe… paṇidhīti? ","html":"{}"},"kv7.7:2.3":{"pli":"Āmantā. ","html":"{}"},"kv7.7:2.4":{"pli":"Pathavī kammavipāko, pathavī sukhavedaniyā dukkhavedaniyā adukkhamasukhavedaniyā sukhāya vedanāya sampayuttā dukkhāya …pe… adukkhamasukhāya vedanāya sampayuttā phassena sampayuttā vedanāya sampayuttā saññāya sampayuttā cetanāya sampayuttā cittena sampayuttā sārammaṇā; ","html":"{}"},"kv7.7:2.5":{"pli":"atthi tāya āvaṭṭanā ābhogo samannāhāro manasikāro cetanā patthanā paṇidhīti? ","html":"{}"},"kv7.7:2.6":{"pli":"Na hevaṃ vattabbe …pe… ","html":"{}"},"kv7.7:2.7":{"pli":"pathavī kammavipāko, pathavī na sukhavedaniyā na dukkhavedaniyā …pe… anārammaṇā; ","html":"{}"},"kv7.7:2.8":{"pli":"natthi tāya āvaṭṭanā …pe… paṇidhīti? ","html":"{}"},"kv7.7:2.9":{"pli":"Āmantā. ","html":"{}"},"kv7.7:2.10":{"pli":"Phasso kammavipāko, phasso na sukhavedaniyo na dukkhavedaniyo …pe… anārammaṇo; ","html":"{}"},"kv7.7:2.11":{"pli":"natthi tassa āvaṭṭanā …pe… paṇidhīti? ","html":"{}"},"kv7.7:2.12":{"pli":"Na hevaṃ vattabbe …pe…. ","html":"{}</p>"},"kv7.7:3.1":{"pli":"Pathavī kammavipākoti? ","html":"<p data-doxy='orthodox'>{}"},"kv7.7:3.2":{"pli":"Āmantā. ","html":"{}"},"kv7.7:3.3":{"pli":"Pathavī paggahaniggahupagā chedanabhedanupagāti? ","html":"{}"},"kv7.7:3.4":{"pli":"Āmantā. ","html":"{}"},"kv7.7:3.5":{"pli":"Kammavipāko paggahaniggahupago chedanabhedanupagoti? ","html":"{}"},"kv7.7:3.6":{"pli":"Na hevaṃ vattabbe …pe…. ","html":"{}</p>"},"kv7.7:4.1":{"pli":"Labbhā pathavī ketuṃ vikketuṃ āṭhapetuṃ ocinituṃ vicinitunti? ","html":"<p data-doxy='orthodox'>{}"},"kv7.7:4.2":{"pli":"Āmantā. ","html":"{}"},"kv7.7:4.3":{"pli":"Labbhā kammavipāko ketuṃ vikketuṃ āṭhapetuṃ ocinituṃ vicinitunti? ","html":"{}"},"kv7.7:4.4":{"pli":"Na hevaṃ vattabbe …pe…. ","html":"{}</p>"},"kv7.7:5.1":{"pli":"Pathavī paresaṃ sādhāraṇāti? ","html":"<p data-doxy='orthodox'>{}"},"kv7.7:5.2":{"pli":"Āmantā. ","html":"{}"},"kv7.7:5.3":{"pli":"Kammavipāko paresaṃ sādhāraṇoti? ","html":"{}"},"kv7.7:5.4":{"pli":"Na hevaṃ vattabbe …pe…. ","html":"{}</p>"},"kv7.7:6.1":{"pli":"Kammavipāko paresaṃ sādhāraṇoti? ","html":"<p>{}"},"kv7.7:6.2":{"pli":"Āmantā. ","html":"{}"},"kv7.7:6.3":{"pli":"Nanu vuttaṃ bhagavatā—","html":"{}</p>"},"kv7.7:7.1":{"pli":"“Asādhāraṇamaññesaṃ, ","html":"<blockquote class='gatha'><p><span class='verse-line'>{}</span>"},"kv7.7:7.2":{"pli":"acoraharaṇo nidhi; ","html":"<span class='verse-line'>{}</span>"},"kv7.7:7.3":{"pli":"Kayirātha macco puññāni, ","html":"<span class='verse-line'>{}</span>"},"kv7.7:7.4":{"pli":"sace sucaritaṃ care”ti. ","html":"<span class='verse-line'>{}</span></p></blockquote>"},"kv7.7:8.1":{"pli":"Attheva suttantoti? ","html":"<p>{}"},"kv7.7:8.2":{"pli":"Āmantā. ","html":"{}"},"kv7.7:8.3":{"pli":"Tena hi na vattabbaṃ—","html":"{}"},"kv7.7:8.4":{"pli":"“kammavipāko paresaṃ sādhāraṇo”ti. ","html":"{}</p>"},"kv7.7:9.1":{"pli":"Pathavī kammavipākoti? ","html":"<p data-doxy='orthodox'>{}"},"kv7.7:9.2":{"pli":"Āmantā. ","html":"{}"},"kv7.7:9.3":{"pli":"Paṭhamaṃ pathavī saṇṭhāti, pacchā sattā uppajjantīti? ","html":"{}"},"kv7.7:9.4":{"pli":"Āmantā. ","html":"{}"},"kv7.7:9.5":{"pli":"Paṭhamaṃ vipāko uppajjati, pacchā vipākapaṭilābhāya kammaṃ karontīti? ","html":"{}"},"kv7.7:9.6":{"pli":"Na hevaṃ vattabbe …pe…. ","html":"{}</p>"},"kv7.7:10.1":{"pli":"Pathavī sabbasattānaṃ kammavipākoti? ","html":"<p data-doxy='orthodox'>{}"},"kv7.7:10.2":{"pli":"Āmantā. ","html":"{}"},"kv7.7:10.3":{"pli":"Sabbe sattā pathaviṃ paribhuñjantīti? ","html":"{}"},"kv7.7:10.4":{"pli":"Na hevaṃ vattabbe …pe… ","html":"{}"},"kv7.7:10.5":{"pli":"sabbe sattā pathaviṃ paribhuñjantīti? ","html":"{}"},"kv7.7:10.6":{"pli":"Āmantā. ","html":"{}"},"kv7.7:10.7":{"pli":"Atthi keci pathaviṃ aparibhuñjitvā parinibbāyantīti? ","html":"{}"},"kv7.7:10.8":{"pli":"Āmantā. ","html":"{}"},"kv7.7:10.9":{"pli":"Atthi keci kammavipākaṃ akhepetvā parinibbāyantīti? ","html":"{}"},"kv7.7:10.10":{"pli":"Na hevaṃ vattabbe …pe…. ","html":"{}</p>"},"kv7.7:11.1":{"pli":"Pathavī cakkavattisattassa kammavipākoti? ","html":"<p data-doxy='orthodox'>{}"},"kv7.7:11.2":{"pli":"Āmantā. ","html":"{}"},"kv7.7:11.3":{"pli":"Aññe sattā pathaviṃ paribhuñjantīti? ","html":"{}"},"kv7.7:11.4":{"pli":"Āmantā. ","html":"{}"},"kv7.7:11.5":{"pli":"Cakkavattisattassa kammavipākaṃ aññe sattā paribhuñjantīti? ","html":"{}"},"kv7.7:11.6":{"pli":"Na hevaṃ vattabbe …pe… ","html":"{}"},"kv7.7:11.7":{"pli":"cakkavattisattassa kammavipākaṃ aññe sattā paribhuñjantīti? ","html":"{}"},"kv7.7:11.8":{"pli":"Āmantā. ","html":"{}"},"kv7.7:11.9":{"pli":"Cakkavattisattassa phassaṃ vedanaṃ saññaṃ cetanaṃ cittaṃ saddhaṃ vīriyaṃ satiṃ samādhiṃ paññaṃ aññe sattā paribhuñjantīti? ","html":"{}"},"kv7.7:11.10":{"pli":"Na hevaṃ vattabbe …pe…. ","html":"{}</p>"},"kv7.7:12.1":{"pli":"Na vattabbaṃ—","html":"<p data-doxy='heterodox'>{}"},"kv7.7:12.2":{"pli":"“pathavī kammavipāko”ti? ","html":"{}"},"kv7.7:12.3":{"pli":"Āmantā. ","html":"{}"},"kv7.7:12.4":{"pli":"Nanu atthi issariyasaṃvattaniyaṃ kammaṃ adhipaccasaṃvattaniyaṃ kammanti? ","html":"{}"},"kv7.7:12.5":{"pli":"Āmantā. ","html":"{}"},"kv7.7:12.6":{"pli":"Hañci atthi issariyasaṃvattaniyaṃ kammaṃ adhipaccasaṃvattaniyaṃ kammaṃ, tena vata re vattabbe—","html":"{}"},"kv7.7:12.7":{"pli":"“pathavī kammavipāko”ti. ","html":"{}</p>"},"kv7.7:12.8":{"pli":"Pathavī kammavipākotikathā niṭṭhitā. ","html":"<p class='endsutta'>{}</p></article>"}},"kv7.8":{"kv7.8:0.1":{"pli":"Kathāvatthu ","html":"<article id='kv7.8'><header><ul><li class='division'>{}</li>"},"kv7.8:0.2":{"pli":"Mahāpaṇṇāsaka ","html":"<li>{}</li>"},"kv7.8:0.3":{"pli":"Sattamavagga ","html":"<li>{}</li></ul>"},"kv7.8:0.4":{"pli":"Jarāmaraṇaṃvipākotikathā ","html":"<h1 class='sutta-title'>{}</h1></header>"},"kv7.8:1.1":{"pli":"Jarāmaraṇaṃ vipākoti? ","html":"<p data-doxy='orthodox'>{}"},"kv7.8:1.2":{"pli":"Āmantā. ","html":"{}"},"kv7.8:1.3":{"pli":"Sukhavedaniyaṃ dukkhavedaniyaṃ adukkhamasukhavedaniyaṃ, sukhāya vedanāya sampayuttaṃ, dukkhāya vedanāya sampayuttaṃ, adukkhamasukhāya vedanāya sampayuttaṃ, phassena sampayuttaṃ, vedanāya sampayuttaṃ, saññāya sampayuttaṃ, cetanāya sampayuttaṃ, cittena sampayuttaṃ, sārammaṇaṃ; ","html":"{}"},"kv7.8:1.4":{"pli":"atthi tassa āvaṭṭanā ābhogo samannāhāro manasikāro cetanā patthanā paṇidhīti? ","html":"{}"},"kv7.8:1.5":{"pli":"Na hevaṃ vattabbe …pe… ","html":"{}"},"kv7.8:1.6":{"pli":"nanu na sukhavedaniyaṃ na dukkhavedaniyaṃ …pe… anārammaṇaṃ; ","html":"{}"},"kv7.8:1.7":{"pli":"natthi tassa āvaṭṭanā …pe… paṇidhīti? ","html":"{}"},"kv7.8:1.8":{"pli":"Āmantā. ","html":"{}"},"kv7.8:1.9":{"pli":"Hañci na sukhavedaniyaṃ na dukkhavedaniyaṃ …pe… anārammaṇaṃ; ","html":"{}"},"kv7.8:1.10":{"pli":"natthi tassa āvaṭṭanā …pe… paṇidhi, no ca vata re vattabbe—","html":"{}"},"kv7.8:1.11":{"pli":"“jarāmaraṇaṃ vipāko”ti. ","html":"{}</p>"},"kv7.8:2.1":{"pli":"Phasso vipāko, phasso sukhavedaniyo dukkhavedaniyo …pe… ","html":"<p data-doxy='orthodox'>{}"},"kv7.8:2.2":{"pli":"sārammaṇo; ","html":"{}"},"kv7.8:2.3":{"pli":"atthi tassa āvaṭṭanā …pe… paṇidhīti? ","html":"{}"},"kv7.8:2.4":{"pli":"Āmantā. ","html":"{}"},"kv7.8:2.5":{"pli":"Jarāmaraṇaṃ vipāko, jarāmaraṇaṃ sukhavedaniyaṃ dukkhavedaniyaṃ …pe… ","html":"{}"},"kv7.8:2.6":{"pli":"sārammaṇaṃ; ","html":"{}"},"kv7.8:2.7":{"pli":"atthi tassa āvaṭṭanā …pe… paṇidhīti? ","html":"{}"},"kv7.8:2.8":{"pli":"Na hevaṃ vattabbe …pe…. ","html":"{}</p>"},"kv7.8:3.1":{"pli":"Jarāmaraṇaṃ vipāko, jarāmaraṇaṃ na sukhavedaniyaṃ na dukkhavedaniyaṃ …pe… anārammaṇaṃ; ","html":"<p data-doxy='orthodox'>{}"},"kv7.8:3.2":{"pli":"natthi tassa āvaṭṭanā …pe… paṇidhīti? ","html":"{}"},"kv7.8:3.3":{"pli":"Āmantā. ","html":"{}"},"kv7.8:3.4":{"pli":"Phasso vipāko, phasso na sukhavedaniyo na dukkhavedaniyo …pe… anārammaṇo; ","html":"{}"},"kv7.8:3.5":{"pli":"natthi tassa āvaṭṭanā …pe… paṇidhīti? ","html":"{}"},"kv7.8:3.6":{"pli":"Na hevaṃ vattabbe …pe…. ","html":"{}</p>"},"kv7.8:4.1":{"pli":"Akusalānaṃ dhammānaṃ jarāmaraṇaṃ, akusalānaṃ dhammānaṃ vipākoti? ","html":"<p data-doxy='orthodox'>{}"},"kv7.8:4.2":{"pli":"Āmantā. ","html":"{}"},"kv7.8:4.3":{"pli":"Kusalānaṃ dhammānaṃ jarāmaraṇaṃ, kusalānaṃ dhammānaṃ vipākoti? ","html":"{}"},"kv7.8:4.4":{"pli":"Na hevaṃ vattabbe …pe…. ","html":"{}</p>"},"kv7.8:5.1":{"pli":"Kusalānaṃ dhammānaṃ jarāmaraṇaṃ, na vattabbaṃ—","html":"<p data-doxy='orthodox'>{}"},"kv7.8:5.2":{"pli":"“kusalānaṃ dhammānaṃ vipāko”ti? ","html":"{}"},"kv7.8:5.3":{"pli":"Āmantā. ","html":"{}"},"kv7.8:5.4":{"pli":"Akusalānaṃ dhammānaṃ jarāmaraṇaṃ, na vattabbaṃ—","html":"{}"},"kv7.8:5.5":{"pli":"“akusalānaṃ dhammānaṃ vipāko”ti? ","html":"{}"},"kv7.8:5.6":{"pli":"Na hevaṃ vattabbe …pe…. ","html":"{}</p>"},"kv7.8:6.1":{"pli":"Kusalānaṃ dhammānaṃ jarāmaraṇaṃ, akusalānaṃ dhammānaṃ vipākoti? ","html":"<p data-doxy='orthodox'>{}"},"kv7.8:6.2":{"pli":"Āmantā. ","html":"{}"},"kv7.8:6.3":{"pli":"Akusalānaṃ dhammānaṃ jarāmaraṇaṃ, kusalānaṃ dhammānaṃ vipākoti? ","html":"{}"},"kv7.8:6.4":{"pli":"Na hevaṃ vattabbe …pe…. ","html":"{}</p>"},"kv7.8:7.1":{"pli":"Akusalānaṃ dhammānaṃ jarāmaraṇaṃ, na vattabbaṃ—","html":"<p data-doxy='orthodox'>{}"},"kv7.8:7.2":{"pli":"“kusalānaṃ dhammānaṃ vipāko”ti? ","html":"{}"},"kv7.8:7.3":{"pli":"Āmantā. ","html":"{}"},"kv7.8:7.4":{"pli":"Kusalānaṃ dhammānaṃ jarāmaraṇaṃ, na vattabbaṃ—","html":"{}"},"kv7.8:7.5":{"pli":"“akusalānaṃ dhammānaṃ vipāko”ti? ","html":"{}"},"kv7.8:7.6":{"pli":"Na hevaṃ vattabbe …pe…. ","html":"{}</p>"},"kv7.8:8.1":{"pli":"Kusalānañca akusalānañca dhammānaṃ jarāmaraṇaṃ, akusalānaṃ dhammānaṃ vipākoti? ","html":"<p data-doxy='orthodox'>{}"},"kv7.8:8.2":{"pli":"Āmantā. ","html":"{}"},"kv7.8:8.3":{"pli":"Kusalānañca akusalānañca dhammānaṃ jarāmaraṇaṃ, kusalānaṃ dhammānaṃ vipākoti? ","html":"{}"},"kv7.8:8.4":{"pli":"Na hevaṃ vattabbe …pe…. ","html":"{}</p>"},"kv7.8:9.1":{"pli":"Kusalānañca akusalānañca dhammānaṃ jarāmaraṇaṃ, na vattabbaṃ—","html":"<p data-doxy='orthodox'>{}"},"kv7.8:9.2":{"pli":"“kusalānaṃ dhammānaṃ vipāko”ti? ","html":"{}"},"kv7.8:9.3":{"pli":"Āmantā. ","html":"{}"},"kv7.8:9.4":{"pli":"Kusalānañca akusalānañca dhammānaṃ jarāmaraṇaṃ, na vattabbaṃ—","html":"{}"},"kv7.8:9.5":{"pli":"“akusalānaṃ dhammānaṃ vipāko”ti? ","html":"{}"},"kv7.8:9.6":{"pli":"Na hevaṃ vattabbe …pe…. ","html":"{}</p>"},"kv7.8:10.1":{"pli":"Na vattabbaṃ—","html":"<p data-doxy='heterodox'>{}"},"kv7.8:10.2":{"pli":"“jarāmaraṇaṃ vipāko”ti? ","html":"{}"},"kv7.8:10.3":{"pli":"Āmantā. ","html":"{}"},"kv7.8:10.4":{"pli":"Nanu atthi dubbaṇṇasaṃvattaniyaṃ kammaṃ appāyukasaṃvattaniyaṃ kammanti? ","html":"{}"},"kv7.8:10.5":{"pli":"Āmantā. ","html":"{}"},"kv7.8:10.6":{"pli":"Hañci atthi dubbaṇṇasaṃvattaniyaṃ kammaṃ appāyukasaṃvattaniyaṃ kammaṃ, tena vata re vattabbe—","html":"{}"},"kv7.8:10.7":{"pli":"“jarāmaraṇaṃ vipāko”ti. ","html":"{}</p>"},"kv7.8:10.8":{"pli":"Jarāmaraṇaṃ vipākotikathā niṭṭhitā. ","html":"<p class='endsutta'>{}</p></article>"}},"kv7.9":{"kv7.9:0.1":{"pli":"Kathāvatthu ","html":"<article id='kv7.9'><header><ul><li class='division'>{}</li>"},"kv7.9:0.2":{"pli":"Mahāpaṇṇāsaka ","html":"<li>{}</li>"},"kv7.9:0.3":{"pli":"Sattamavagga ","html":"<li>{}</li></ul>"},"kv7.9:0.4":{"pli":"Ariyadhammavipākakathā ","html":"<h1 class='sutta-title'>{}</h1></header>"},"kv7.9:1.1":{"pli":"Natthi ariyadhammavipākoti? ","html":"<p data-doxy='orthodox'>{}"},"kv7.9:1.2":{"pli":"Āmantā. ","html":"{}"},"kv7.9:1.3":{"pli":"Nanu mahapphalaṃ sāmaññaṃ mahapphalaṃ brahmaññanti? ","html":"{}"},"kv7.9:1.4":{"pli":"Āmantā. ","html":"{}"},"kv7.9:1.5":{"pli":"Hañci mahapphalaṃ sāmaññaṃ mahapphalaṃ brahmaññaṃ, no ca vata re vattabbe—","html":"{}"},"kv7.9:1.6":{"pli":"“natthi ariyadhammavipāko”ti. ","html":"{}</p>"},"kv7.9:2.1":{"pli":"Natthi ariyadhammavipākoti? ","html":"<p data-doxy='orthodox'>{}"},"kv7.9:2.2":{"pli":"Āmantā. ","html":"{}"},"kv7.9:2.3":{"pli":"Nanu atthi sotāpattiphalanti? ","html":"{}"},"kv7.9:2.4":{"pli":"Āmantā. ","html":"{}"},"kv7.9:2.5":{"pli":"Hañci atthi sotāpattiphalaṃ, no ca vata re vattabbe—","html":"{}"},"kv7.9:2.6":{"pli":"“natthi ariyadhammavipāko”ti. ","html":"{}"},"kv7.9:2.7":{"pli":"Nanu atthi sakadāgāmiphalaṃ …pe… ","html":"{}"},"kv7.9:2.8":{"pli":"anāgāmiphalaṃ …pe… ","html":"{}"},"kv7.9:2.9":{"pli":"arahattaphalanti? ","html":"{}"},"kv7.9:2.10":{"pli":"Āmantā. ","html":"{}"},"kv7.9:2.11":{"pli":"Hañci atthi arahattaphalaṃ, no ca vata re vattabbe—","html":"{}"},"kv7.9:2.12":{"pli":"“natthi ariyadhammavipāko”ti. ","html":"{}</p>"},"kv7.9:3.1":{"pli":"Sotāpattiphalaṃ na vipākoti? ","html":"<p data-doxy='orthodox'>{}"},"kv7.9:3.2":{"pli":"Āmantā. ","html":"{}"},"kv7.9:3.3":{"pli":"Dānaphalaṃ na vipākoti? ","html":"{}"},"kv7.9:3.4":{"pli":"Na hevaṃ vattabbe …pe… ","html":"{}"},"kv7.9:3.5":{"pli":"sotāpattiphalaṃ na vipākoti? ","html":"{}"},"kv7.9:3.6":{"pli":"Āmantā. ","html":"{}"},"kv7.9:3.7":{"pli":"Sīlaphalaṃ …pe… ","html":"{}"},"kv7.9:3.8":{"pli":"bhāvanāphalaṃ na vipākoti? ","html":"{}"},"kv7.9:3.9":{"pli":"Na hevaṃ vattabbe …pe…. ","html":"{}</p>"},"kv7.9:4.1":{"pli":"Sakadāgāmiphalaṃ …pe… ","html":"<p data-doxy='orthodox'>{}"},"kv7.9:4.2":{"pli":"anāgāmiphalaṃ …pe… ","html":"{}"},"kv7.9:4.3":{"pli":"arahattaphalaṃ na vipākoti? ","html":"{}"},"kv7.9:4.4":{"pli":"Āmantā. ","html":"{}"},"kv7.9:4.5":{"pli":"Dānaphalaṃ na vipākoti? ","html":"{}"},"kv7.9:4.6":{"pli":"Na hevaṃ vattabbe …pe… ","html":"{}"},"kv7.9:4.7":{"pli":"arahattaphalaṃ na vipākoti? ","html":"{}"},"kv7.9:4.8":{"pli":"Āmantā. ","html":"{}"},"kv7.9:4.9":{"pli":"Sīlaphalaṃ …pe… ","html":"{}"},"kv7.9:4.10":{"pli":"bhāvanāphalaṃ na vipākoti? ","html":"{}"},"kv7.9:4.11":{"pli":"Na hevaṃ vattabbe …pe… ","html":"{}"},"kv7.9:4.12":{"pli":"dānaphalaṃ vipākoti? ","html":"{}"},"kv7.9:4.13":{"pli":"Āmantā. ","html":"{}"},"kv7.9:4.14":{"pli":"Sotāpattiphalaṃ vipākoti? ","html":"{}"},"kv7.9:4.15":{"pli":"Na hevaṃ vattabbe …pe… ","html":"{}</p>"},"kv7.9:5.1":{"pli":"Dānaphalaṃ vipākoti? ","html":"<p data-doxy='orthodox'>{}"},"kv7.9:5.2":{"pli":"Āmantā. ","html":"{}"},"kv7.9:5.3":{"pli":"Sakadāgāmiphalaṃ …pe… ","html":"{}"},"kv7.9:5.4":{"pli":"anāgāmiphalaṃ …pe… ","html":"{}"},"kv7.9:5.5":{"pli":"arahattaphalaṃ vipākoti? ","html":"{}"},"kv7.9:5.6":{"pli":"Na hevaṃ vattabbe …pe… ","html":"{}"},"kv7.9:5.7":{"pli":"sīlaphalaṃ …pe… ","html":"{}"},"kv7.9:5.8":{"pli":"bhāvanāphalaṃ vipākoti? ","html":"{}"},"kv7.9:5.9":{"pli":"Āmantā. ","html":"{}"},"kv7.9:5.10":{"pli":"Sotāpattiphalaṃ vipākoti? ","html":"{}"},"kv7.9:5.11":{"pli":"Na hevaṃ vattabbe …pe… ","html":"{}"},"kv7.9:5.12":{"pli":"bhāvanāphalaṃ vipākoti? ","html":"{}"},"kv7.9:5.13":{"pli":"Āmantā. ","html":"{}"},"kv7.9:5.14":{"pli":"Sakadāgāmiphalaṃ …pe… ","html":"{}"},"kv7.9:5.15":{"pli":"anāgāmiphalaṃ …pe… ","html":"{}"},"kv7.9:5.16":{"pli":"arahattaphalaṃ vipākoti? ","html":"{}"},"kv7.9:5.17":{"pli":"Na hevaṃ vattabbe …pe…. ","html":"{}</p>"},"kv7.9:6.1":{"pli":"Kāmāvacaraṃ kusalaṃ savipākanti? ","html":"<p data-doxy='orthodox'>{}"},"kv7.9:6.2":{"pli":"Āmantā. ","html":"{}"},"kv7.9:6.3":{"pli":"Lokuttaraṃ kusalaṃ savipākanti? ","html":"{}"},"kv7.9:6.4":{"pli":"Na hevaṃ vattabbe …pe… ","html":"{}"},"kv7.9:6.5":{"pli":"rūpāvacaraṃ kusalaṃ …pe… ","html":"{}"},"kv7.9:6.6":{"pli":"arūpāvacaraṃ kusalaṃ savipākanti? ","html":"{}"},"kv7.9:6.7":{"pli":"Āmantā. ","html":"{}"},"kv7.9:6.8":{"pli":"Lokuttaraṃ kusalaṃ savipākanti? ","html":"{}"},"kv7.9:6.9":{"pli":"Na hevaṃ vattabbe …pe…. ","html":"{}</p>"},"kv7.9:7.1":{"pli":"Lokuttaraṃ kusalaṃ avipākanti? ","html":"<p data-doxy='orthodox'>{}"},"kv7.9:7.2":{"pli":"Āmantā. ","html":"{}"},"kv7.9:7.3":{"pli":"Kāmāvacaraṃ kusalaṃ avipākanti? ","html":"{}"},"kv7.9:7.4":{"pli":"Na hevaṃ vattabbe …pe… ","html":"{}"},"kv7.9:7.5":{"pli":"lokuttaraṃ kusalaṃ avipākanti? ","html":"{}"},"kv7.9:7.6":{"pli":"Āmantā. ","html":"{}"},"kv7.9:7.7":{"pli":"Rūpāvacaraṃ …pe… ","html":"{}"},"kv7.9:7.8":{"pli":"arūpāvacaraṃ kusalaṃ avipākanti? ","html":"{}"},"kv7.9:7.9":{"pli":"Na hevaṃ vattabbe …pe…. ","html":"{}</p>"},"kv7.9:8.1":{"pli":"Kāmāvacaraṃ kusalaṃ savipākaṃ ācayagāmīti? ","html":"<p data-doxy='heterodox'>{}"},"kv7.9:8.2":{"pli":"Āmantā. ","html":"{}"},"kv7.9:8.3":{"pli":"Lokuttaraṃ kusalaṃ savipākaṃ ācayagāmīti? ","html":"{}"},"kv7.9:8.4":{"pli":"Na hevaṃ vattabbe …pe… ","html":"{}"},"kv7.9:8.5":{"pli":"rūpāvacaraṃ …pe… ","html":"{}"},"kv7.9:8.6":{"pli":"arūpāvacaraṃ kusalaṃ savipākaṃ ācayagāmīti? ","html":"{}"},"kv7.9:8.7":{"pli":"Āmantā. ","html":"{}"},"kv7.9:8.8":{"pli":"Lokuttaraṃ kusalaṃ savipākaṃ ācayagāmīti? ","html":"{}"},"kv7.9:8.9":{"pli":"Na hevaṃ vattabbe …pe…. ","html":"{}</p>"},"kv7.9:9.1":{"pli":"Lokuttaraṃ kusalaṃ savipākaṃ apacayagāmīti? ","html":"<p data-doxy='heterodox'>{}"},"kv7.9:9.2":{"pli":"Āmantā. ","html":"{}"},"kv7.9:9.3":{"pli":"Kāmāvacaraṃ kusalaṃ savipākaṃ apacayagāmīti? ","html":"{}"},"kv7.9:9.4":{"pli":"Na hevaṃ vattabbe …pe…. ","html":"{}"},"kv7.9:9.5":{"pli":"Lokuttaraṃ kusalaṃ savipākaṃ apacayagāmīti? ","html":"{}"},"kv7.9:9.6":{"pli":"Āmantā. ","html":"{}"},"kv7.9:9.7":{"pli":"Rūpāvacaraṃ …pe… ","html":"{}"},"kv7.9:9.8":{"pli":"arūpāvacaraṃ kusalaṃ savipākaṃ apacayagāmīti? ","html":"{}"},"kv7.9:9.9":{"pli":"Na hevaṃ vattabbe …pe…. ","html":"{}</p>"},"kv7.9:9.10":{"pli":"Ariyadhammavipākakathā niṭṭhitā. ","html":"<p class='endsutta'>{}</p></article>"}},"kv8.1":{"kv8.1:0.1":{"pli":"Kathāvatthu ","html":"<article id='kv8.1'><header><ul><li class='division'>{}</li>"},"kv8.1:0.2":{"pli":"Niyāmapaṇṇāsaka ","html":"<li>{}</li>"},"kv8.1:0.3":{"pli":"Aṭṭhamavagga ","html":"<li>{}</li></ul>"},"kv8.1:0.4":{"pli":"Chagatikathā ","html":"<h1 class='sutta-title'>{}</h1></header>"},"kv8.1:1.1":{"pli":"Cha gatiyoti? ","html":"<p data-doxy='orthodox'>{}"},"kv8.1:1.2":{"pli":"Āmantā. ","html":"{}"},"kv8.1:1.3":{"pli":"Nanu pañca gatiyo vuttā bhagavatā—","html":"{}"},"kv8.1:1.4":{"pli":"“nirayo, tiracchānayoni, pettivisayo, manussā, devā”ti? ","html":"{}"},"kv8.1:1.5":{"pli":"Āmantā. ","html":"{}"},"kv8.1:1.6":{"pli":"Hañci pañca gatiyo vuttā bhagavatā—","html":"{}"},"kv8.1:1.7":{"pli":"nirayo, tiracchānayoni, pettivisayo, manussā, devā; ","html":"{}"},"kv8.1:1.8":{"pli":"no ca vata re vattabbe—","html":"{}"},"kv8.1:1.9":{"pli":"“cha gatiyo”ti. ","html":"{}</p>"},"kv8.1:2.1":{"pli":"Cha gatiyoti? ","html":"<p data-doxy='orthodox'>{}"},"kv8.1:2.2":{"pli":"Āmantā. ","html":"{}"},"kv8.1:2.3":{"pli":"Nanu kālakañcikā asurā petānaṃ samānavaṇṇā samānabhogā samānāhārā samānāyukā petehi saha āvāhavivāhaṃ gacchantīti? ","html":"{}"},"kv8.1:2.4":{"pli":"Āmantā. ","html":"{}"},"kv8.1:2.5":{"pli":"Hañci kālakañcikā asurā petānaṃ samānavaṇṇā samānabhogā samānāhārā samānāyukā petehi saha āvāhavivāhaṃ gacchanti, no ca vata re vattabbe—","html":"{}"},"kv8.1:2.6":{"pli":"“cha gatiyo”ti. ","html":"{}</p>"},"kv8.1:3.1":{"pli":"Cha gatiyoti? ","html":"<p data-doxy='orthodox'>{}"},"kv8.1:3.2":{"pli":"Āmantā. ","html":"{}"},"kv8.1:3.3":{"pli":"Nanu vepacittiparisā devānaṃ samānavaṇṇā samānabhogā samānāhārā samānāyukā devehi saha āvāhavivāhaṃ gacchantīti? ","html":"{}"},"kv8.1:3.4":{"pli":"Āmantā. ","html":"{}"},"kv8.1:3.5":{"pli":"Hañci vepacittiparisā devānaṃ samānavaṇṇā samānabhogā samānāhārā samānāyukā devehi saha āvāhavivāhaṃ gacchanti, no ca vata re vattabbe—","html":"{}"},"kv8.1:3.6":{"pli":"“cha gatiyo”ti. ","html":"{}</p>"},"kv8.1:4.1":{"pli":"Cha gatiyoti? ","html":"<p data-doxy='orthodox'>{}"},"kv8.1:4.2":{"pli":"Āmantā. ","html":"{}"},"kv8.1:4.3":{"pli":"Nanu vepacittiparisā pubbadevāti? ","html":"{}"},"kv8.1:4.4":{"pli":"Āmantā. ","html":"{}"},"kv8.1:4.5":{"pli":"Hañci vepacittiparisā pubbadevā, no ca vata re vattabbe—","html":"{}"},"kv8.1:4.6":{"pli":"“cha gatiyo”ti. ","html":"{}</p>"},"kv8.1:5.1":{"pli":"Na vattabbaṃ—","html":"<p data-doxy='heterodox'>{}"},"kv8.1:5.2":{"pli":"“cha gatiyo”ti? ","html":"{}"},"kv8.1:5.3":{"pli":"Āmantā. ","html":"{}"},"kv8.1:5.4":{"pli":"Nanu atthi asurakāyoti? ","html":"{}"},"kv8.1:5.5":{"pli":"Āmantā. ","html":"{}"},"kv8.1:5.6":{"pli":"Hañci atthi asurakāyo, tena vata re vattabbe—","html":"{}"},"kv8.1:5.7":{"pli":"“cha gatiyo”ti. ","html":"{}</p>"},"kv8.1:5.8":{"pli":"Chagatikathā niṭṭhitā. ","html":"<p class='endsutta'>{}</p></article>"}}}